[
  {
    "日期": "2025-12-21",
    "品牌": "六福",
    "产品": "金条金价(内地)",
    "价格": "1191.00",
    "价格_数值": 1191.0,
    "单位": "元/克",
    "纯度": "--",
    "手工费": "另计",
    "涨跌": "涨",
    "黄金类型": "金条",
    "黄金类型代码": "gold_bar",
    "数据来源": "新浪财经",
    "解析时间": "2025-12-21T03:26:02.611297"
  },
  {
    "日期": "2025-12-21",
    "品牌": "周生生",
    "产品": "金条金价(内地)",
    "价格": "1192.00",
    "价格_数值": 1192.0,
    "单位": "元/克",
    "纯度": "--",
    "手工费": "另计",
    "涨跌": "涨",
    "黄金类型": "金条",
    "黄金类型代码": "gold_bar",
    "数据来源": "新浪财经",
    "解析时间": "2025-12-21T03:26:02.611311"
  },
  {
    "日期": "2025-12-21",
    "品牌": "周大福",
    "产品": "金条金价(内地)",
    "价格": "1193.00",
    "价格_数值": 1193.0,
    "单位": "元/克",
    "纯度": "--",
    "手工费": "另计",
    "涨跌": "涨",
    "黄金类型": "金条",
    "黄金类型代码": "gold_bar",
    "数据来源": "新浪财经",
    "解析时间": "2025-12-21T03:26:02.611315"
  },
  {
    "日期": "2025-12-20",
    "品牌": "周大福",
    "产品": "金条金价(内地)",
    "价格": "1193.00",
    "价格_数值": 1193.0,
    "单位": "元/克",
    "纯度": "--",
    "手工费": "另计",
    "涨跌": "涨",
    "黄金类型": "金条",
    "黄金类型代码": "gold_bar",
    "数据来源": "新浪财经",
    "解析时间": "2025-12-21T03:26:02.611318"
  },
  {
    "日期": "2025-12-20",
    "品牌": "周生生",
    "产品": "金条金价(内地)",
    "价格": "1192.00",
    "价格_数值": 1192.0,
    "单位": "元/克",
    "纯度": "--",
    "手工费": "另计",
    "涨跌": "涨",
    "黄金类型": "金条",
    "黄金类型代码": "gold_bar",
    "数据来源": "新浪财经",
    "解析时间": "2025-12-21T03:26:02.611321"
  },
  {
    "日期": "2025-12-20",
    "品牌": "六福",
    "产品": "金条金价(内地)",
    "价格": "1191.00",
    "价格_数值": 1191.0,
    "单位": "元/克",
    "纯度": "--",
    "手工费": "另计",
    "涨跌": "涨",
    "黄金类型": "金条",
    "黄金类型代码": "gold_bar",
    "数据来源": "新浪财经",
    "解析时间": "2025-12-21T03:26:02.611324"
  },
  {
    "日期": "2025-12-19",
    "品牌": "周大福",
    "产品": "金条金价(内地)",
    "价格": "1187.00",
    "价格_数值": 1187.0,
    "单位": "元/克",
    "纯度": "--",
    "手工费": "另计",
    "涨跌": "--",
    "黄金类型": "金条",
    "黄金类型代码": "gold_bar",
    "数据来源": "新浪财经",
    "解析时间": "2025-12-21T03:26:02.611327"
  },
  {
    "日期": "2025-12-19",
    "品牌": "周生生",
    "产品": "金条金价(内地)",
    "价格": "1188.00",
    "价格_数值": 1188.0,
    "单位": "元/克",
    "纯度": "--",
    "手工费": "另计",
    "涨跌": "跌",
    "黄金类型": "金条",
    "黄金类型代码": "gold_bar",
    "数据来源": "新浪财经",
    "解析时间": "2025-12-21T03:26:02.611330"
  },
  {
    "日期": "2025-12-19",
    "品牌": "六福",
    "产品": "金条金价(内地)",
    "价格": "1185.00",
    "价格_数值": 1185.0,
    "单位": "元/克",
    "纯度": "--",
    "手工费": "另计",
    "涨跌": "--",
    "黄金类型": "金条",
    "黄金类型代码": "gold_bar",
    "数据来源": "新浪财经",
    "解析时间": "2025-12-21T03:26:02.611332"
  },
  {
    "日期": "2025-12-18",
    "品牌": "周大福",
    "产品": "金条金价(内地)",
    "价格": "1187.00",
    "价格_数值": 1187.0,
    "单位": "元/克",
    "纯度": "--",
    "手工费": "另计",
    "涨跌": "--",
    "黄金类型": "金条",
    "黄金类型代码": "gold_bar",
    "数据来源": "新浪财经",
    "解析时间": "2025-12-21T03:26:02.611335"
  },
  {
    "日期": "2025-12-18",
    "品牌": "六福",
    "产品": "金条金价(内地)",
    "价格": "1185.00",
    "价格_数值": 1185.0,
    "单位": "元/克",
    "纯度": "--",
    "手工费": "另计",
    "涨跌": "--",
    "黄金类型": "金条",
    "黄金类型代码": "gold_bar",
    "数据来源": "新浪财经",
    "解析时间": "2025-12-21T03:26:02.611338"
  },
  {
    "日期": "2025-12-18",
    "品牌": "周生生",
    "产品": "金条金价(内地)",
    "价格": "1190.00",
    "价格_数值": 1190.0,
    "单位": "元/克",
    "纯度": "--",
    "手工费": "另计",
    "涨跌": "涨",
    "黄金类型": "金条",
    "黄金类型代码": "gold_bar",
    "数据来源": "新浪财经",
    "解析时间": "2025-12-21T03:26:02.611341"
  },
  {
    "日期": "2025-12-17",
    "品牌": "周大福",
    "产品": "金条金价(内地)",
    "价格": "1187.00",
    "价格_数值": 1187.0,
    "单位": "元/克",
    "纯度": "--",
    "手工费": "另计",
    "涨跌": "--",
    "黄金类型": "金条",
    "黄金类型代码": "gold_bar",
    "数据来源": "新浪财经",
    "解析时间": "2025-12-21T03:26:02.611344"
  },
  {
    "日期": "2025-12-17",
    "品牌": "周生生",
    "产品": "金条金价(内地)",
    "价格": "1186.00",
    "价格_数值": 1186.0,
    "单位": "元/克",
    "纯度": "--",
    "手工费": "另计",
    "涨跌": "涨",
    "黄金类型": "金条",
    "黄金类型代码": "gold_bar",
    "数据来源": "新浪财经",
    "解析时间": "2025-12-21T03:26:02.611347"
  },
  {
    "日期": "2025-12-17",
    "品牌": "六福",
    "产品": "金条金价(内地)",
    "价格": "1185.00",
    "价格_数值": 1185.0,
    "单位": "元/克",
    "纯度": "--",
    "手工费": "另计",
    "涨跌": "--",
    "黄金类型": "金条",
    "黄金类型代码": "gold_bar",
    "数据来源": "新浪财经",
    "解析时间": "2025-12-21T03:26:02.611349"
  },
  {
    "日期": "2025-12-16",
    "品牌": "周生生",
    "产品": "金条金价(内地)",
    "价格": "1184.00",
    "价格_数值": 1184.0,
    "单位": "元/克",
    "纯度": "--",
    "手工费": "另计",
    "涨跌": "跌",
    "黄金类型": "金条",
    "黄金类型代码": "gold_bar",
    "数据来源": "新浪财经",
    "解析时间": "2025-12-21T03:26:02.611352"
  },
  {
    "日期": "2025-12-16",
    "品牌": "周大福",
    "产品": "金条金价(内地)",
    "价格": "1187.00",
    "价格_数值": 1187.0,
    "单位": "元/克",
    "纯度": "--",
    "手工费": "另计",
    "涨跌": "--",
    "黄金类型": "金条",
    "黄金类型代码": "gold_bar",
    "数据来源": "新浪财经",
    "解析时间": "2025-12-21T03:26:02.611355"
  },
  {
    "日期": "2025-12-16",
    "品牌": "六福",
    "产品": "金条金价(内地)",
    "价格": "1185.00",
    "价格_数值": 1185.0,
    "单位": "元/克",
    "纯度": "--",
    "手工费": "另计",
    "涨跌": "--",
    "黄金类型": "金条",
    "黄金类型代码": "gold_bar",
    "数据来源": "新浪财经",
    "解析时间": "2025-12-21T03:26:02.611358"
  },
  {
    "日期": "2025-12-15",
    "品牌": "六福",
    "产品": "金条金价(内地)",
    "价格": "1185.00",
    "价格_数值": 1185.0,
    "单位": "元/克",
    "纯度": "--",
    "手工费": "另计",
    "涨跌": "涨",
    "黄金类型": "金条",
    "黄金类型代码": "gold_bar",
    "数据来源": "新浪财经",
    "解析时间": "2025-12-21T03:26:02.611360"
  },
  {
    "日期": "2025-12-15",
    "品牌": "周生生",
    "产品": "金条金价(内地)",
    "价格": "1187.00",
    "价格_数值": 1187.0,
    "单位": "元/克",
    "纯度": "--",
    "手工费": "另计",
    "涨跌": "涨",
    "黄金类型": "金条",
    "黄金类型代码": "gold_bar",
    "数据来源": "新浪财经",
    "解析时间": "2025-12-21T03:26:02.611368"
  },
  {
    "日期": "2025-12-15",
    "品牌": "周大福",
    "产品": "金条金价(内地)",
    "价格": "1187.00",
    "价格_数值": 1187.0,
    "单位": "元/克",
    "纯度": "--",
    "手工费": "另计",
    "涨跌": "涨",
    "黄金类型": "金条",
    "黄金类型代码": "gold_bar",
    "数据来源": "新浪财经",
    "解析时间": "2025-12-21T03:26:02.611371"
  },
  {
    "日期": "2025-12-14",
    "品牌": "周大福",
    "产品": "金条金价(内地)",
    "价格": "1182.00",
    "价格_数值": 1182.0,
    "单位": "元/克",
    "纯度": "--",
    "手工费": "另计",
    "涨跌": "涨",
    "黄金类型": "金条",
    "黄金类型代码": "gold_bar",
    "数据来源": "新浪财经",
    "解析时间": "2025-12-21T03:26:02.611374"
  },
  {
    "日期": "2025-12-14",
    "品牌": "周生生",
    "产品": "金条金价(内地)",
    "价格": "1185.00",
    "价格_数值": 1185.0,
    "单位": "元/克",
    "纯度": "--",
    "手工费": "另计",
    "涨跌": "涨",
    "黄金类型": "金条",
    "黄金类型代码": "gold_bar",
    "数据来源": "新浪财经",
    "解析时间": "2025-12-21T03:26:02.611376"
  },
  {
    "日期": "2025-12-14",
    "品牌": "六福",
    "产品": "金条金价(内地)",
    "价格": "1180.00",
    "价格_数值": 1180.0,
    "单位": "元/克",
    "纯度": "--",
    "手工费": "另计",
    "涨跌": "涨",
    "黄金类型": "金条",
    "黄金类型代码": "gold_bar",
    "数据来源": "新浪财经",
    "解析时间": "2025-12-21T03:26:02.611379"
  },
  {
    "日期": "2025-12-13",
    "品牌": "六福",
    "产品": "金条金价(内地)",
    "价格": "1180.00",
    "价格_数值": 1180.0,
    "单位": "元/克",
    "纯度": "--",
    "手工费": "另计",
    "涨跌": "涨",
    "黄金类型": "金条",
    "黄金类型代码": "gold_bar",
    "数据来源": "新浪财经",
    "解析时间": "2025-12-21T03:26:02.611382"
  },
  {
    "日期": "2025-12-13",
    "品牌": "周生生",
    "产品": "金条金价(内地)",
    "价格": "1185.00",
    "价格_数值": 1185.0,
    "单位": "元/克",
    "纯度": "--",
    "手工费": "另计",
    "涨跌": "涨",
    "黄金类型": "金条",
    "黄金类型代码": "gold_bar",
    "数据来源": "新浪财经",
    "解析时间": "2025-12-21T03:26:02.611384"
  },
  {
    "日期": "2025-12-13",
    "品牌": "周大福",
    "产品": "金条金价(内地)",
    "价格": "1182.00",
    "价格_数值": 1182.0,
    "单位": "元/克",
    "纯度": "--",
    "手工费": "另计",
    "涨跌": "涨",
    "黄金类型": "金条",
    "黄金类型代码": "gold_bar",
    "数据来源": "新浪财经",
    "解析时间": "2025-12-21T03:26:02.611387"
  },
  {
    "日期": "2025-12-12",
    "品牌": "周生生",
    "产品": "金条金价(内地)",
    "价格": "1173.00",
    "价格_数值": 1173.0,
    "单位": "元/克",
    "纯度": "--",
    "手工费": "另计",
    "涨跌": "--",
    "黄金类型": "金条",
    "黄金类型代码": "gold_bar",
    "数据来源": "新浪财经",
    "解析时间": "2025-12-21T03:26:02.611390"
  },
  {
    "日期": "2025-12-12",
    "品牌": "周大福",
    "产品": "金条金价(内地)",
    "价格": "1172.00",
    "价格_数值": 1172.0,
    "单位": "元/克",
    "纯度": "--",
    "手工费": "另计",
    "涨跌": "--",
    "黄金类型": "金条",
    "黄金类型代码": "gold_bar",
    "数据来源": "新浪财经",
    "解析时间": "2025-12-21T03:26:02.611392"
  },
  {
    "日期": "2025-12-12",
    "品牌": "六福",
    "产品": "金条金价(内地)",
    "价格": "1170.00",
    "价格_数值": 1170.0,
    "单位": "元/克",
    "纯度": "--",
    "手工费": "另计",
    "涨跌": "--",
    "黄金类型": "金条",
    "黄金类型代码": "gold_bar",
    "数据来源": "新浪财经",
    "解析时间": "2025-12-21T03:26:02.611399"
  },
  {
    "日期": "2025-12-11",
    "品牌": "周大福",
    "产品": "金条金价(内地)",
    "价格": "1172.00",
    "价格_数值": 1172.0,
    "单位": "元/克",
    "纯度": "--",
    "手工费": "另计",
    "涨跌": "涨",
    "黄金类型": "金条",
    "黄金类型代码": "gold_bar",
    "数据来源": "新浪财经",
    "解析时间": "2025-12-21T03:26:02.611402"
  },
  {
    "日期": "2025-12-11",
    "品牌": "周生生",
    "产品": "金条金价(内地)",
    "价格": "1173.00",
    "价格_数值": 1173.0,
    "单位": "元/克",
    "纯度": "--",
    "手工费": "另计",
    "涨跌": "涨",
    "黄金类型": "金条",
    "黄金类型代码": "gold_bar",
    "数据来源": "新浪财经",
    "解析时间": "2025-12-21T03:26:02.611404"
  },
  {
    "日期": "2025-12-11",
    "品牌": "六福",
    "产品": "金条金价(内地)",
    "价格": "1170.00",
    "价格_数值": 1170.0,
    "单位": "元/克",
    "纯度": "--",
    "手工费": "另计",
    "涨跌": "涨",
    "黄金类型": "金条",
    "黄金类型代码": "gold_bar",
    "数据来源": "新浪财经",
    "解析时间": "2025-12-21T03:26:02.611407"
  },
  {
    "日期": "2025-12-10",
    "品牌": "六福",
    "产品": "金条金价(内地)",
    "价格": "1163.00",
    "价格_数值": 1163.0,
    "单位": "元/克",
    "纯度": "--",
    "手工费": "另计",
    "涨跌": "--",
    "黄金类型": "金条",
    "黄金类型代码": "gold_bar",
    "数据来源": "新浪财经",
    "解析时间": "2025-12-21T03:26:02.611410"
  },
  {
    "日期": "2025-12-10",
    "品牌": "周生生",
    "产品": "金条金价(内地)",
    "价格": "1165.00",
    "价格_数值": 1165.0,
    "单位": "元/克",
    "纯度": "--",
    "手工费": "另计",
    "涨跌": "涨",
    "黄金类型": "金条",
    "黄金类型代码": "gold_bar",
    "数据来源": "新浪财经",
    "解析时间": "2025-12-21T03:26:02.611412"
  },
  {
    "日期": "2025-12-10",
    "品牌": "周大福",
    "产品": "金条金价(内地)",
    "价格": "1165.00",
    "价格_数值": 1165.0,
    "单位": "元/克",
    "纯度": "--",
    "手工费": "另计",
    "涨跌": "--",
    "黄金类型": "金条",
    "黄金类型代码": "gold_bar",
    "数据来源": "新浪财经",
    "解析时间": "2025-12-21T03:26:02.611415"
  },
  {
    "日期": "2025-12-09",
    "品牌": "周大福",
    "产品": "金条金价(内地)",
    "价格": "1165.00",
    "价格_数值": 1165.0,
    "单位": "元/克",
    "纯度": "--",
    "手工费": "另计",
    "涨跌": "--",
    "黄金类型": "金条",
    "黄金类型代码": "gold_bar",
    "数据来源": "新浪财经",
    "解析时间": "2025-12-21T03:26:02.611418"
  },
  {
    "日期": "2025-12-09",
    "品牌": "周生生",
    "产品": "金条金价(内地)",
    "价格": "1161.00",
    "价格_数值": 1161.0,
    "单位": "元/克",
    "纯度": "--",
    "手工费": "另计",
    "涨跌": "跌",
    "黄金类型": "金条",
    "黄金类型代码": "gold_bar",
    "数据来源": "新浪财经",
    "解析时间": "2025-12-21T03:26:02.611420"
  },
  {
    "日期": "2025-12-09",
    "品牌": "六福",
    "产品": "金条金价(内地)",
    "价格": "1163.00",
    "价格_数值": 1163.0,
    "单位": "元/克",
    "纯度": "--",
    "手工费": "另计",
    "涨跌": "--",
    "黄金类型": "金条",
    "黄金类型代码": "gold_bar",
    "数据来源": "新浪财经",
    "解析时间": "2025-12-21T03:26:02.611423"
  },
  {
    "日期": "2025-12-08",
    "品牌": "周生生",
    "产品": "金条金价(内地)",
    "价格": "1164.00",
    "价格_数值": 1164.0,
    "单位": "元/克",
    "纯度": "--",
    "手工费": "另计",
    "涨跌": "涨",
    "黄金类型": "金条",
    "黄金类型代码": "gold_bar",
    "数据来源": "新浪财经",
    "解析时间": "2025-12-21T03:26:02.611426"
  },
  {
    "日期": "2025-12-08",
    "品牌": "六福",
    "产品": "金条金价(内地)",
    "价格": "1163.00",
    "价格_数值": 1163.0,
    "单位": "元/克",
    "纯度": "--",
    "手工费": "另计",
    "涨跌": "--",
    "黄金类型": "金条",
    "黄金类型代码": "gold_bar",
    "数据来源": "新浪财经",
    "解析时间": "2025-12-21T03:26:02.611429"
  },
  {
    "日期": "2025-12-08",
    "品牌": "周大福",
    "产品": "金条金价(内地)",
    "价格": "1165.00",
    "价格_数值": 1165.0,
    "单位": "元/克",
    "纯度": "--",
    "手工费": "另计",
    "涨跌": "--",
    "黄金类型": "金条",
    "黄金类型代码": "gold_bar",
    "数据来源": "新浪财经",
    "解析时间": "2025-12-21T03:26:02.611432"
  },
  {
    "日期": "2025-12-07",
    "品牌": "周大福",
    "产品": "金条金价(内地)",
    "价格": "1165.00",
    "价格_数值": 1165.0,
    "单位": "元/克",
    "纯度": "--",
    "手工费": "另计",
    "涨跌": "--",
    "黄金类型": "金条",
    "黄金类型代码": "gold_bar",
    "数据来源": "新浪财经",
    "解析时间": "2025-12-21T03:26:02.611434"
  },
  {
    "日期": "2025-12-07",
    "品牌": "六福",
    "产品": "金条金价(内地)",
    "价格": "1163.00",
    "价格_数值": 1163.0,
    "单位": "元/克",
    "纯度": "--",
    "手工费": "另计",
    "涨跌": "--",
    "黄金类型": "金条",
    "黄金类型代码": "gold_bar",
    "数据来源": "新浪财经",
    "解析时间": "2025-12-21T03:26:02.611437"
  },
  {
    "日期": "2025-12-07",
    "品牌": "周生生",
    "产品": "金条金价(内地)",
    "价格": "1161.00",
    "价格_数值": 1161.0,
    "单位": "元/克",
    "纯度": "--",
    "手工费": "另计",
    "涨跌": "跌",
    "黄金类型": "金条",
    "黄金类型代码": "gold_bar",
    "数据来源": "新浪财经",
    "解析时间": "2025-12-21T03:26:02.611440"
  },
  {
    "日期": "2025-12-06",
    "品牌": "周大福",
    "产品": "金条金价(内地)",
    "价格": "1165.00",
    "价格_数值": 1165.0,
    "单位": "元/克",
    "纯度": "--",
    "手工费": "另计",
    "涨跌": "--",
    "黄金类型": "金条",
    "黄金类型代码": "gold_bar",
    "数据来源": "新浪财经",
    "解析时间": "2025-12-21T03:26:02.611442"
  },
  {
    "日期": "2025-12-06",
    "品牌": "六福",
    "产品": "金条金价(内地)",
    "价格": "1163.00",
    "价格_数值": 1163.0,
    "单位": "元/克",
    "纯度": "--",
    "手工费": "另计",
    "涨跌": "--",
    "黄金类型": "金条",
    "黄金类型代码": "gold_bar",
    "数据来源": "新浪财经",
    "解析时间": "2025-12-21T03:26:02.611445"
  },
  {
    "日期": "2025-12-06",
    "品牌": "周生生",
    "产品": "金条金价(内地)",
    "价格": "1161.00",
    "价格_数值": 1161.0,
    "单位": "元/克",
    "纯度": "--",
    "手工费": "另计",
    "涨跌": "跌",
    "黄金类型": "金条",
    "黄金类型代码": "gold_bar",
    "数据来源": "新浪财经",
    "解析时间": "2025-12-21T03:26:02.611448"
  },
  {
    "日期": "2025-12-05",
    "品牌": "周生生",
    "产品": "金条金价(内地)",
    "价格": "1162.00",
    "价格_数值": 1162.0,
    "单位": "元/克",
    "纯度": "--",
    "手工费": "另计",
    "涨跌": "跌",
    "黄金类型": "金条",
    "黄金类型代码": "gold_bar",
    "数据来源": "新浪财经",
    "解析时间": "2025-12-21T03:26:02.611451"
  },
  {
    "日期": "2025-12-05",
    "品牌": "周大福",
    "产品": "金条金价(内地)",
    "价格": "1165.00",
    "价格_数值": 1165.0,
    "单位": "元/克",
    "纯度": "--",
    "手工费": "另计",
    "涨跌": "--",
    "黄金类型": "金条",
    "黄金类型代码": "gold_bar",
    "数据来源": "新浪财经",
    "解析时间": "2025-12-21T03:26:02.611455"
  }
]