[
  {
    "日期": "2026-05-07",
    "品牌": "六福",
    "产品": "黄金价格",
    "价格": "1435.00",
    "价格_数值": 1435.0,
    "单位": "元/克",
    "纯度": "--",
    "手工费": "另计",
    "涨跌": "涨",
    "黄金类型": "实物黄金",
    "黄金类型代码": "physical",
    "数据来源": "新浪财经",
    "解析时间": "2026-05-07T05:28:13.506204"
  },
  {
    "日期": "2026-05-07",
    "品牌": "周生生",
    "产品": "黄金价格",
    "价格": "1438.00",
    "价格_数值": 1438.0,
    "单位": "元/克",
    "纯度": "--",
    "手工费": "另计",
    "涨跌": "涨",
    "黄金类型": "实物黄金",
    "黄金类型代码": "physical",
    "数据来源": "新浪财经",
    "解析时间": "2026-05-07T05:28:13.506220"
  },
  {
    "日期": "2026-05-07",
    "品牌": "周大福",
    "产品": "黄金价格",
    "价格": "1437.00",
    "价格_数值": 1437.0,
    "单位": "元/克",
    "纯度": "--",
    "手工费": "另计",
    "涨跌": "涨",
    "黄金类型": "实物黄金",
    "黄金类型代码": "physical",
    "数据来源": "新浪财经",
    "解析时间": "2026-05-07T05:28:13.506223"
  },
  {
    "日期": "2026-05-07",
    "品牌": "菜百",
    "产品": "黄金价格",
    "价格": "1405.00",
    "价格_数值": 1405.0,
    "单位": "元/克",
    "纯度": "--",
    "手工费": "另计",
    "涨跌": "涨",
    "黄金类型": "实物黄金",
    "黄金类型代码": "physical",
    "数据来源": "新浪财经",
    "解析时间": "2026-05-07T05:28:13.506227"
  },
  {
    "日期": "2026-05-07",
    "品牌": "金至尊",
    "产品": "黄金价格",
    "价格": "1435.00",
    "价格_数值": 1435.0,
    "单位": "元/克",
    "纯度": "--",
    "手工费": "另计",
    "涨跌": "涨",
    "黄金类型": "实物黄金",
    "黄金类型代码": "physical",
    "数据来源": "新浪财经",
    "解析时间": "2026-05-07T05:28:13.506230"
  },
  {
    "日期": "2026-05-07",
    "品牌": "老庙",
    "产品": "黄金价格",
    "价格": "1435.00",
    "价格_数值": 1435.0,
    "单位": "元/克",
    "纯度": "--",
    "手工费": "另计",
    "涨跌": "涨",
    "黄金类型": "实物黄金",
    "黄金类型代码": "physical",
    "数据来源": "新浪财经",
    "解析时间": "2026-05-07T05:28:13.506233"
  },
  {
    "日期": "2026-05-06",
    "品牌": "周生生",
    "产品": "黄金价格",
    "价格": "1413.00",
    "价格_数值": 1413.0,
    "单位": "元/克",
    "纯度": "--",
    "手工费": "另计",
    "涨跌": "涨",
    "黄金类型": "实物黄金",
    "黄金类型代码": "physical",
    "数据来源": "新浪财经",
    "解析时间": "2026-05-07T05:28:13.506236"
  },
  {
    "日期": "2026-05-06",
    "品牌": "六福",
    "产品": "黄金价格",
    "价格": "1411.00",
    "价格_数值": 1411.0,
    "单位": "元/克",
    "纯度": "--",
    "手工费": "另计",
    "涨跌": "涨",
    "黄金类型": "实物黄金",
    "黄金类型代码": "physical",
    "数据来源": "新浪财经",
    "解析时间": "2026-05-07T05:28:13.506239"
  },
  {
    "日期": "2026-05-06",
    "品牌": "金至尊",
    "产品": "黄金价格",
    "价格": "1411.00",
    "价格_数值": 1411.0,
    "单位": "元/克",
    "纯度": "--",
    "手工费": "另计",
    "涨跌": "涨",
    "黄金类型": "实物黄金",
    "黄金类型代码": "physical",
    "数据来源": "新浪财经",
    "解析时间": "2026-05-07T05:28:13.506242"
  },
  {
    "日期": "2026-05-06",
    "品牌": "老庙",
    "产品": "黄金价格",
    "价格": "1418.00",
    "价格_数值": 1418.0,
    "单位": "元/克",
    "纯度": "--",
    "手工费": "另计",
    "涨跌": "涨",
    "黄金类型": "实物黄金",
    "黄金类型代码": "physical",
    "数据来源": "新浪财经",
    "解析时间": "2026-05-07T05:28:13.506245"
  },
  {
    "日期": "2026-05-06",
    "品牌": "菜百",
    "产品": "黄金价格",
    "价格": "1378.00",
    "价格_数值": 1378.0,
    "单位": "元/克",
    "纯度": "--",
    "手工费": "另计",
    "涨跌": "--",
    "黄金类型": "实物黄金",
    "黄金类型代码": "physical",
    "数据来源": "新浪财经",
    "解析时间": "2026-05-07T05:28:13.506248"
  },
  {
    "日期": "2026-05-06",
    "品牌": "周大福",
    "产品": "黄金价格",
    "价格": "1413.00",
    "价格_数值": 1413.0,
    "单位": "元/克",
    "纯度": "--",
    "手工费": "另计",
    "涨跌": "涨",
    "黄金类型": "实物黄金",
    "黄金类型代码": "physical",
    "数据来源": "新浪财经",
    "解析时间": "2026-05-07T05:28:13.506251"
  },
  {
    "日期": "2026-05-05",
    "品牌": "菜百",
    "产品": "黄金价格",
    "价格": "1378.00",
    "价格_数值": 1378.0,
    "单位": "元/克",
    "纯度": "--",
    "手工费": "另计",
    "涨跌": "跌",
    "黄金类型": "实物黄金",
    "黄金类型代码": "physical",
    "数据来源": "新浪财经",
    "解析时间": "2026-05-07T05:28:13.506254"
  },
  {
    "日期": "2026-05-05",
    "品牌": "老庙",
    "产品": "黄金价格",
    "价格": "1392.00",
    "价格_数值": 1392.0,
    "单位": "元/克",
    "纯度": "--",
    "手工费": "另计",
    "涨跌": "跌",
    "黄金类型": "实物黄金",
    "黄金类型代码": "physical",
    "数据来源": "新浪财经",
    "解析时间": "2026-05-07T05:28:13.506257"
  },
  {
    "日期": "2026-05-05",
    "品牌": "周大福",
    "产品": "黄金价格",
    "价格": "1392.00",
    "价格_数值": 1392.0,
    "单位": "元/克",
    "纯度": "--",
    "手工费": "另计",
    "涨跌": "跌",
    "黄金类型": "实物黄金",
    "黄金类型代码": "physical",
    "数据来源": "新浪财经",
    "解析时间": "2026-05-07T05:28:13.506260"
  },
  {
    "日期": "2026-05-05",
    "品牌": "六福",
    "产品": "黄金价格",
    "价格": "1390.00",
    "价格_数值": 1390.0,
    "单位": "元/克",
    "纯度": "--",
    "手工费": "另计",
    "涨跌": "跌",
    "黄金类型": "实物黄金",
    "黄金类型代码": "physical",
    "数据来源": "新浪财经",
    "解析时间": "2026-05-07T05:28:13.506263"
  },
  {
    "日期": "2026-05-05",
    "品牌": "金至尊",
    "产品": "黄金价格",
    "价格": "1390.00",
    "价格_数值": 1390.0,
    "单位": "元/克",
    "纯度": "--",
    "手工费": "另计",
    "涨跌": "跌",
    "黄金类型": "实物黄金",
    "黄金类型代码": "physical",
    "数据来源": "新浪财经",
    "解析时间": "2026-05-07T05:28:13.506265"
  },
  {
    "日期": "2026-05-05",
    "品牌": "周生生",
    "产品": "黄金价格",
    "价格": "1393.00",
    "价格_数值": 1393.0,
    "单位": "元/克",
    "纯度": "--",
    "手工费": "另计",
    "涨跌": "跌",
    "黄金类型": "实物黄金",
    "黄金类型代码": "physical",
    "数据来源": "新浪财经",
    "解析时间": "2026-05-07T05:28:13.506268"
  },
  {
    "日期": "2026-05-04",
    "品牌": "周大福",
    "产品": "黄金价格",
    "价格": "1419.00",
    "价格_数值": 1419.0,
    "单位": "元/克",
    "纯度": "--",
    "手工费": "另计",
    "涨跌": "--",
    "黄金类型": "实物黄金",
    "黄金类型代码": "physical",
    "数据来源": "新浪财经",
    "解析时间": "2026-05-07T05:28:13.506271"
  },
  {
    "日期": "2026-05-04",
    "品牌": "周生生",
    "产品": "黄金价格",
    "价格": "1410.00",
    "价格_数值": 1410.0,
    "单位": "元/克",
    "纯度": "--",
    "手工费": "另计",
    "涨跌": "跌",
    "黄金类型": "实物黄金",
    "黄金类型代码": "physical",
    "数据来源": "新浪财经",
    "解析时间": "2026-05-07T05:28:13.506274"
  },
  {
    "日期": "2026-05-04",
    "品牌": "金至尊",
    "产品": "黄金价格",
    "价格": "1417.00",
    "价格_数值": 1417.0,
    "单位": "元/克",
    "纯度": "--",
    "手工费": "另计",
    "涨跌": "--",
    "黄金类型": "实物黄金",
    "黄金类型代码": "physical",
    "数据来源": "新浪财经",
    "解析时间": "2026-05-07T05:28:13.506277"
  },
  {
    "日期": "2026-05-04",
    "品牌": "六福",
    "产品": "黄金价格",
    "价格": "1417.00",
    "价格_数值": 1417.0,
    "单位": "元/克",
    "纯度": "--",
    "手工费": "另计",
    "涨跌": "--",
    "黄金类型": "实物黄金",
    "黄金类型代码": "physical",
    "数据来源": "新浪财经",
    "解析时间": "2026-05-07T05:28:13.506280"
  },
  {
    "日期": "2026-05-04",
    "品牌": "菜百",
    "产品": "黄金价格",
    "价格": "1388.00",
    "价格_数值": 1388.0,
    "单位": "元/克",
    "纯度": "--",
    "手工费": "另计",
    "涨跌": "--",
    "黄金类型": "实物黄金",
    "黄金类型代码": "physical",
    "数据来源": "新浪财经",
    "解析时间": "2026-05-07T05:28:13.506283"
  },
  {
    "日期": "2026-05-04",
    "品牌": "老庙",
    "产品": "黄金价格",
    "价格": "1416.00",
    "价格_数值": 1416.0,
    "单位": "元/克",
    "纯度": "--",
    "手工费": "另计",
    "涨跌": "涨",
    "黄金类型": "实物黄金",
    "黄金类型代码": "physical",
    "数据来源": "新浪财经",
    "解析时间": "2026-05-07T05:28:13.506286"
  },
  {
    "日期": "2026-05-02",
    "品牌": "金至尊",
    "产品": "黄金价格",
    "价格": "1417.00",
    "价格_数值": 1417.0,
    "单位": "元/克",
    "纯度": "--",
    "手工费": "另计",
    "涨跌": "--",
    "黄金类型": "实物黄金",
    "黄金类型代码": "physical",
    "数据来源": "新浪财经",
    "解析时间": "2026-05-07T05:28:13.506288"
  },
  {
    "日期": "2026-05-02",
    "品牌": "周生生",
    "产品": "黄金价格",
    "价格": "1416.00",
    "价格_数值": 1416.0,
    "单位": "元/克",
    "纯度": "--",
    "手工费": "另计",
    "涨跌": "涨",
    "黄金类型": "实物黄金",
    "黄金类型代码": "physical",
    "数据来源": "新浪财经",
    "解析时间": "2026-05-07T05:28:13.506291"
  },
  {
    "日期": "2026-05-02",
    "品牌": "老庙",
    "产品": "黄金价格",
    "价格": "1410.00",
    "价格_数值": 1410.0,
    "单位": "元/克",
    "纯度": "--",
    "手工费": "另计",
    "涨跌": "--",
    "黄金类型": "实物黄金",
    "黄金类型代码": "physical",
    "数据来源": "新浪财经",
    "解析时间": "2026-05-07T05:28:13.506294"
  },
  {
    "日期": "2026-05-02",
    "品牌": "菜百",
    "产品": "黄金价格",
    "价格": "1388.00",
    "价格_数值": 1388.0,
    "单位": "元/克",
    "纯度": "--",
    "手工费": "另计",
    "涨跌": "--",
    "黄金类型": "实物黄金",
    "黄金类型代码": "physical",
    "数据来源": "新浪财经",
    "解析时间": "2026-05-07T05:28:13.506297"
  },
  {
    "日期": "2026-05-02",
    "品牌": "周大福",
    "产品": "黄金价格",
    "价格": "1419.00",
    "价格_数值": 1419.0,
    "单位": "元/克",
    "纯度": "--",
    "手工费": "另计",
    "涨跌": "--",
    "黄金类型": "实物黄金",
    "黄金类型代码": "physical",
    "数据来源": "新浪财经",
    "解析时间": "2026-05-07T05:28:13.506300"
  },
  {
    "日期": "2026-05-02",
    "品牌": "六福",
    "产品": "黄金价格",
    "价格": "1417.00",
    "价格_数值": 1417.0,
    "单位": "元/克",
    "纯度": "--",
    "手工费": "另计",
    "涨跌": "--",
    "黄金类型": "实物黄金",
    "黄金类型代码": "physical",
    "数据来源": "新浪财经",
    "解析时间": "2026-05-07T05:28:13.506303"
  },
  {
    "日期": "2026-05-01",
    "品牌": "菜百",
    "产品": "黄金价格",
    "价格": "1388.00",
    "价格_数值": 1388.0,
    "单位": "元/克",
    "纯度": "--",
    "手工费": "另计",
    "涨跌": "--",
    "黄金类型": "实物黄金",
    "黄金类型代码": "physical",
    "数据来源": "新浪财经",
    "解析时间": "2026-05-07T05:28:13.506306"
  },
  {
    "日期": "2026-05-01",
    "品牌": "六福",
    "产品": "黄金价格",
    "价格": "1417.00",
    "价格_数值": 1417.0,
    "单位": "元/克",
    "纯度": "--",
    "手工费": "另计",
    "涨跌": "涨",
    "黄金类型": "实物黄金",
    "黄金类型代码": "physical",
    "数据来源": "新浪财经",
    "解析时间": "2026-05-07T05:28:13.506308"
  },
  {
    "日期": "2026-05-01",
    "品牌": "周大福",
    "产品": "黄金价格",
    "价格": "1419.00",
    "价格_数值": 1419.0,
    "单位": "元/克",
    "纯度": "--",
    "手工费": "另计",
    "涨跌": "涨",
    "黄金类型": "实物黄金",
    "黄金类型代码": "physical",
    "数据来源": "新浪财经",
    "解析时间": "2026-05-07T05:28:13.506311"
  },
  {
    "日期": "2026-05-01",
    "品牌": "金至尊",
    "产品": "黄金价格",
    "价格": "1417.00",
    "价格_数值": 1417.0,
    "单位": "元/克",
    "纯度": "--",
    "手工费": "另计",
    "涨跌": "涨",
    "黄金类型": "实物黄金",
    "黄金类型代码": "physical",
    "数据来源": "新浪财经",
    "解析时间": "2026-05-07T05:28:13.506314"
  },
  {
    "日期": "2026-05-01",
    "品牌": "周生生",
    "产品": "黄金价格",
    "价格": "1415.00",
    "价格_数值": 1415.0,
    "单位": "元/克",
    "纯度": "--",
    "手工费": "另计",
    "涨跌": "涨",
    "黄金类型": "实物黄金",
    "黄金类型代码": "physical",
    "数据来源": "新浪财经",
    "解析时间": "2026-05-07T05:28:13.506317"
  },
  {
    "日期": "2026-05-01",
    "品牌": "老庙",
    "产品": "黄金价格",
    "价格": "1410.00",
    "价格_数值": 1410.0,
    "单位": "元/克",
    "纯度": "--",
    "手工费": "另计",
    "涨跌": "涨",
    "黄金类型": "实物黄金",
    "黄金类型代码": "physical",
    "数据来源": "新浪财经",
    "解析时间": "2026-05-07T05:28:13.506320"
  },
  {
    "日期": "2026-04-30",
    "品牌": "周生生",
    "产品": "黄金价格",
    "价格": "1406.00",
    "价格_数值": 1406.0,
    "单位": "元/克",
    "纯度": "--",
    "手工费": "另计",
    "涨跌": "涨",
    "黄金类型": "实物黄金",
    "黄金类型代码": "physical",
    "数据来源": "新浪财经",
    "解析时间": "2026-05-07T05:28:13.506323"
  },
  {
    "日期": "2026-04-30",
    "品牌": "六福",
    "产品": "黄金价格",
    "价格": "1408.00",
    "价格_数值": 1408.0,
    "单位": "元/克",
    "纯度": "--",
    "手工费": "另计",
    "涨跌": "--",
    "黄金类型": "实物黄金",
    "黄金类型代码": "physical",
    "数据来源": "新浪财经",
    "解析时间": "2026-05-07T05:28:13.506325"
  },
  {
    "日期": "2026-04-30",
    "品牌": "金至尊",
    "产品": "黄金价格",
    "价格": "1408.00",
    "价格_数值": 1408.0,
    "单位": "元/克",
    "纯度": "--",
    "手工费": "另计",
    "涨跌": "--",
    "黄金类型": "实物黄金",
    "黄金类型代码": "physical",
    "数据来源": "新浪财经",
    "解析时间": "2026-05-07T05:28:13.506328"
  },
  {
    "日期": "2026-04-30",
    "品牌": "周大福",
    "产品": "黄金价格",
    "价格": "1410.00",
    "价格_数值": 1410.0,
    "单位": "元/克",
    "纯度": "--",
    "手工费": "另计",
    "涨跌": "--",
    "黄金类型": "实物黄金",
    "黄金类型代码": "physical",
    "数据来源": "新浪财经",
    "解析时间": "2026-05-07T05:28:13.506332"
  },
  {
    "日期": "2026-04-30",
    "品牌": "菜百",
    "产品": "黄金价格",
    "价格": "1388.00",
    "价格_数值": 1388.0,
    "单位": "元/克",
    "纯度": "--",
    "手工费": "另计",
    "涨跌": "跌",
    "黄金类型": "实物黄金",
    "黄金类型代码": "physical",
    "数据来源": "新浪财经",
    "解析时间": "2026-05-07T05:28:13.506334"
  },
  {
    "日期": "2026-04-30",
    "品牌": "老庙",
    "产品": "黄金价格",
    "价格": "1406.00",
    "价格_数值": 1406.0,
    "单位": "元/克",
    "纯度": "--",
    "手工费": "另计",
    "涨跌": "跌",
    "黄金类型": "实物黄金",
    "黄金类型代码": "physical",
    "数据来源": "新浪财经",
    "解析时间": "2026-05-07T05:28:13.506340"
  },
  {
    "日期": "2026-04-29",
    "品牌": "周生生",
    "产品": "黄金价格",
    "价格": "1404.00",
    "价格_数值": 1404.0,
    "单位": "元/克",
    "纯度": "--",
    "手工费": "另计",
    "涨跌": "跌",
    "黄金类型": "实物黄金",
    "黄金类型代码": "physical",
    "数据来源": "新浪财经",
    "解析时间": "2026-05-07T05:28:13.506343"
  },
  {
    "日期": "2026-04-29",
    "品牌": "六福",
    "产品": "黄金价格",
    "价格": "1408.00",
    "价格_数值": 1408.0,
    "单位": "元/克",
    "纯度": "--",
    "手工费": "另计",
    "涨跌": "跌",
    "黄金类型": "实物黄金",
    "黄金类型代码": "physical",
    "数据来源": "新浪财经",
    "解析时间": "2026-05-07T05:28:13.506346"
  },
  {
    "日期": "2026-04-29",
    "品牌": "金至尊",
    "产品": "黄金价格",
    "价格": "1408.00",
    "价格_数值": 1408.0,
    "单位": "元/克",
    "纯度": "--",
    "手工费": "另计",
    "涨跌": "跌",
    "黄金类型": "实物黄金",
    "黄金类型代码": "physical",
    "数据来源": "新浪财经",
    "解析时间": "2026-05-07T05:28:13.506349"
  },
  {
    "日期": "2026-04-29",
    "品牌": "老庙",
    "产品": "黄金价格",
    "价格": "1415.00",
    "价格_数值": 1415.0,
    "单位": "元/克",
    "纯度": "--",
    "手工费": "另计",
    "涨跌": "跌",
    "黄金类型": "实物黄金",
    "黄金类型代码": "physical",
    "数据来源": "新浪财经",
    "解析时间": "2026-05-07T05:28:13.506352"
  },
  {
    "日期": "2026-04-29",
    "品牌": "周大福",
    "产品": "黄金价格",
    "价格": "1410.00",
    "价格_数值": 1410.0,
    "单位": "元/克",
    "纯度": "--",
    "手工费": "另计",
    "涨跌": "跌",
    "黄金类型": "实物黄金",
    "黄金类型代码": "physical",
    "数据来源": "新浪财经",
    "解析时间": "2026-05-07T05:28:13.506354"
  },
  {
    "日期": "2026-04-29",
    "品牌": "菜百",
    "产品": "黄金价格",
    "价格": "1395.00",
    "价格_数值": 1395.0,
    "单位": "元/克",
    "纯度": "--",
    "手工费": "另计",
    "涨跌": "跌",
    "黄金类型": "实物黄金",
    "黄金类型代码": "physical",
    "数据来源": "新浪财经",
    "解析时间": "2026-05-07T05:28:13.506357"
  },
  {
    "日期": "2026-04-28",
    "品牌": "周大福",
    "产品": "黄金价格",
    "价格": "1442.00",
    "价格_数值": 1442.0,
    "单位": "元/克",
    "纯度": "--",
    "手工费": "另计",
    "涨跌": "--",
    "黄金类型": "实物黄金",
    "黄金类型代码": "physical",
    "数据来源": "新浪财经",
    "解析时间": "2026-05-07T05:28:13.506360"
  },
  {
    "日期": "2026-04-28",
    "品牌": "周生生",
    "产品": "黄金价格",
    "价格": "1438.00",
    "价格_数值": 1438.0,
    "单位": "元/克",
    "纯度": "--",
    "手工费": "另计",
    "涨跌": "涨",
    "黄金类型": "实物黄金",
    "黄金类型代码": "physical",
    "数据来源": "新浪财经",
    "解析时间": "2026-05-07T05:28:13.506363"
  }
]