[
  {
    "日期": "2026-05-30",
    "品牌": "周生生",
    "产品": "黄金价格",
    "价格": "1380.00",
    "价格_数值": 1380.0,
    "单位": "元/克",
    "纯度": "--",
    "手工费": "另计",
    "涨跌": "涨",
    "黄金类型": "实物黄金",
    "黄金类型代码": "physical",
    "数据来源": "新浪财经",
    "解析时间": "2026-05-31T06:13:35.741428"
  },
  {
    "日期": "2026-05-30",
    "品牌": "六福",
    "产品": "黄金价格",
    "价格": "1374.00",
    "价格_数值": 1374.0,
    "单位": "元/克",
    "纯度": "--",
    "手工费": "另计",
    "涨跌": "涨",
    "黄金类型": "实物黄金",
    "黄金类型代码": "physical",
    "数据来源": "新浪财经",
    "解析时间": "2026-05-31T06:13:35.741447"
  },
  {
    "日期": "2026-05-30",
    "品牌": "金至尊",
    "产品": "黄金价格",
    "价格": "1374.00",
    "价格_数值": 1374.0,
    "单位": "元/克",
    "纯度": "--",
    "手工费": "另计",
    "涨跌": "涨",
    "黄金类型": "实物黄金",
    "黄金类型代码": "physical",
    "数据来源": "新浪财经",
    "解析时间": "2026-05-31T06:13:35.741451"
  },
  {
    "日期": "2026-05-30",
    "品牌": "菜百",
    "产品": "黄金价格",
    "价格": "1355.00",
    "价格_数值": 1355.0,
    "单位": "元/克",
    "纯度": "--",
    "手工费": "另计",
    "涨跌": "--",
    "黄金类型": "实物黄金",
    "黄金类型代码": "physical",
    "数据来源": "新浪财经",
    "解析时间": "2026-05-31T06:13:35.741454"
  },
  {
    "日期": "2026-05-30",
    "品牌": "老庙",
    "产品": "黄金价格",
    "价格": "1373.00",
    "价格_数值": 1373.0,
    "单位": "元/克",
    "纯度": "--",
    "手工费": "另计",
    "涨跌": "涨",
    "黄金类型": "实物黄金",
    "黄金类型代码": "physical",
    "数据来源": "新浪财经",
    "解析时间": "2026-05-31T06:13:35.741457"
  },
  {
    "日期": "2026-05-30",
    "品牌": "周大福",
    "产品": "黄金价格",
    "价格": "1376.00",
    "价格_数值": 1376.0,
    "单位": "元/克",
    "纯度": "--",
    "手工费": "另计",
    "涨跌": "涨",
    "黄金类型": "实物黄金",
    "黄金类型代码": "physical",
    "数据来源": "新浪财经",
    "解析时间": "2026-05-31T06:13:35.741460"
  },
  {
    "日期": "2026-05-29",
    "品牌": "六福",
    "产品": "黄金价格",
    "价格": "1363.00",
    "价格_数值": 1363.0,
    "单位": "元/克",
    "纯度": "--",
    "手工费": "另计",
    "涨跌": "涨",
    "黄金类型": "实物黄金",
    "黄金类型代码": "physical",
    "数据来源": "新浪财经",
    "解析时间": "2026-05-31T06:13:35.741463"
  },
  {
    "日期": "2026-05-29",
    "品牌": "周大福",
    "产品": "黄金价格",
    "价格": "1365.00",
    "价格_数值": 1365.0,
    "单位": "元/克",
    "纯度": "--",
    "手工费": "另计",
    "涨跌": "涨",
    "黄金类型": "实物黄金",
    "黄金类型代码": "physical",
    "数据来源": "新浪财经",
    "解析时间": "2026-05-31T06:13:35.741469"
  },
  {
    "日期": "2026-05-29",
    "品牌": "老庙",
    "产品": "黄金价格",
    "价格": "1368.00",
    "价格_数值": 1368.0,
    "单位": "元/克",
    "纯度": "--",
    "手工费": "另计",
    "涨跌": "涨",
    "黄金类型": "实物黄金",
    "黄金类型代码": "physical",
    "数据来源": "新浪财经",
    "解析时间": "2026-05-31T06:13:35.741472"
  },
  {
    "日期": "2026-05-29",
    "品牌": "菜百",
    "产品": "黄金价格",
    "价格": "1355.00",
    "价格_数值": 1355.0,
    "单位": "元/克",
    "纯度": "--",
    "手工费": "另计",
    "涨跌": "--",
    "黄金类型": "实物黄金",
    "黄金类型代码": "physical",
    "数据来源": "新浪财经",
    "解析时间": "2026-05-31T06:13:35.741475"
  },
  {
    "日期": "2026-05-29",
    "品牌": "周生生",
    "产品": "黄金价格",
    "价格": "1366.00",
    "价格_数值": 1366.0,
    "单位": "元/克",
    "纯度": "--",
    "手工费": "另计",
    "涨跌": "涨",
    "黄金类型": "实物黄金",
    "黄金类型代码": "physical",
    "数据来源": "新浪财经",
    "解析时间": "2026-05-31T06:13:35.741478"
  },
  {
    "日期": "2026-05-29",
    "品牌": "金至尊",
    "产品": "黄金价格",
    "价格": "1363.00",
    "价格_数值": 1363.0,
    "单位": "元/克",
    "纯度": "--",
    "手工费": "另计",
    "涨跌": "涨",
    "黄金类型": "实物黄金",
    "黄金类型代码": "physical",
    "数据来源": "新浪财经",
    "解析时间": "2026-05-31T06:13:35.741481"
  },
  {
    "日期": "2026-05-28",
    "品牌": "菜百",
    "产品": "黄金价格",
    "价格": "1355.00",
    "价格_数值": 1355.0,
    "单位": "元/克",
    "纯度": "--",
    "手工费": "另计",
    "涨跌": "跌",
    "黄金类型": "实物黄金",
    "黄金类型代码": "physical",
    "数据来源": "新浪财经",
    "解析时间": "2026-05-31T06:13:35.741484"
  },
  {
    "日期": "2026-05-28",
    "品牌": "老庙",
    "产品": "黄金价格",
    "价格": "1355.00",
    "价格_数值": 1355.0,
    "单位": "元/克",
    "纯度": "--",
    "手工费": "另计",
    "涨跌": "跌",
    "黄金类型": "实物黄金",
    "黄金类型代码": "physical",
    "数据来源": "新浪财经",
    "解析时间": "2026-05-31T06:13:35.741487"
  },
  {
    "日期": "2026-05-28",
    "品牌": "六福",
    "产品": "黄金价格",
    "价格": "1351.00",
    "价格_数值": 1351.0,
    "单位": "元/克",
    "纯度": "--",
    "手工费": "另计",
    "涨跌": "跌",
    "黄金类型": "实物黄金",
    "黄金类型代码": "physical",
    "数据来源": "新浪财经",
    "解析时间": "2026-05-31T06:13:35.741490"
  },
  {
    "日期": "2026-05-28",
    "品牌": "金至尊",
    "产品": "黄金价格",
    "价格": "1351.00",
    "价格_数值": 1351.0,
    "单位": "元/克",
    "纯度": "--",
    "手工费": "另计",
    "涨跌": "跌",
    "黄金类型": "实物黄金",
    "黄金类型代码": "physical",
    "数据来源": "新浪财经",
    "解析时间": "2026-05-31T06:13:35.741493"
  },
  {
    "日期": "2026-05-28",
    "品牌": "周生生",
    "产品": "黄金价格",
    "价格": "1350.00",
    "价格_数值": 1350.0,
    "单位": "元/克",
    "纯度": "--",
    "手工费": "另计",
    "涨跌": "跌",
    "黄金类型": "实物黄金",
    "黄金类型代码": "physical",
    "数据来源": "新浪财经",
    "解析时间": "2026-05-31T06:13:35.741496"
  },
  {
    "日期": "2026-05-28",
    "品牌": "周大福",
    "产品": "黄金价格",
    "价格": "1353.00",
    "价格_数值": 1353.0,
    "单位": "元/克",
    "纯度": "--",
    "手工费": "另计",
    "涨跌": "跌",
    "黄金类型": "实物黄金",
    "黄金类型代码": "physical",
    "数据来源": "新浪财经",
    "解析时间": "2026-05-31T06:13:35.741501"
  },
  {
    "日期": "2026-05-27",
    "品牌": "老庙",
    "产品": "黄金价格",
    "价格": "1377.00",
    "价格_数值": 1377.0,
    "单位": "元/克",
    "纯度": "--",
    "手工费": "另计",
    "涨跌": "跌",
    "黄金类型": "实物黄金",
    "黄金类型代码": "physical",
    "数据来源": "新浪财经",
    "解析时间": "2026-05-31T06:13:35.741504"
  },
  {
    "日期": "2026-05-27",
    "品牌": "六福",
    "产品": "黄金价格",
    "价格": "1373.00",
    "价格_数值": 1373.0,
    "单位": "元/克",
    "纯度": "--",
    "手工费": "另计",
    "涨跌": "跌",
    "黄金类型": "实物黄金",
    "黄金类型代码": "physical",
    "数据来源": "新浪财经",
    "解析时间": "2026-05-31T06:13:35.741507"
  },
  {
    "日期": "2026-05-27",
    "品牌": "金至尊",
    "产品": "黄金价格",
    "价格": "1373.00",
    "价格_数值": 1373.0,
    "单位": "元/克",
    "纯度": "--",
    "手工费": "另计",
    "涨跌": "跌",
    "黄金类型": "实物黄金",
    "黄金类型代码": "physical",
    "数据来源": "新浪财经",
    "解析时间": "2026-05-31T06:13:35.741510"
  },
  {
    "日期": "2026-05-27",
    "品牌": "周生生",
    "产品": "黄金价格",
    "价格": "1376.00",
    "价格_数值": 1376.0,
    "单位": "元/克",
    "纯度": "--",
    "手工费": "另计",
    "涨跌": "跌",
    "黄金类型": "实物黄金",
    "黄金类型代码": "physical",
    "数据来源": "新浪财经",
    "解析时间": "2026-05-31T06:13:35.741513"
  },
  {
    "日期": "2026-05-27",
    "品牌": "周大福",
    "产品": "黄金价格",
    "价格": "1375.00",
    "价格_数值": 1375.0,
    "单位": "元/克",
    "纯度": "--",
    "手工费": "另计",
    "涨跌": "跌",
    "黄金类型": "实物黄金",
    "黄金类型代码": "physical",
    "数据来源": "新浪财经",
    "解析时间": "2026-05-31T06:13:35.741515"
  },
  {
    "日期": "2026-05-27",
    "品牌": "菜百",
    "产品": "黄金价格",
    "价格": "1370.00",
    "价格_数值": 1370.0,
    "单位": "元/克",
    "纯度": "--",
    "手工费": "另计",
    "涨跌": "--",
    "黄金类型": "实物黄金",
    "黄金类型代码": "physical",
    "数据来源": "新浪财经",
    "解析时间": "2026-05-31T06:13:35.741518"
  },
  {
    "日期": "2026-05-26",
    "品牌": "周大福",
    "产品": "黄金价格",
    "价格": "1386.00",
    "价格_数值": 1386.0,
    "单位": "元/克",
    "纯度": "--",
    "手工费": "另计",
    "涨跌": "跌",
    "黄金类型": "实物黄金",
    "黄金类型代码": "physical",
    "数据来源": "新浪财经",
    "解析时间": "2026-05-31T06:13:35.741521"
  },
  {
    "日期": "2026-05-26",
    "品牌": "周生生",
    "产品": "黄金价格",
    "价格": "1384.00",
    "价格_数值": 1384.0,
    "单位": "元/克",
    "纯度": "--",
    "手工费": "另计",
    "涨跌": "跌",
    "黄金类型": "实物黄金",
    "黄金类型代码": "physical",
    "数据来源": "新浪财经",
    "解析时间": "2026-05-31T06:13:35.741524"
  },
  {
    "日期": "2026-05-26",
    "品牌": "六福",
    "产品": "黄金价格",
    "价格": "1384.00",
    "价格_数值": 1384.0,
    "单位": "元/克",
    "纯度": "--",
    "手工费": "另计",
    "涨跌": "跌",
    "黄金类型": "实物黄金",
    "黄金类型代码": "physical",
    "数据来源": "新浪财经",
    "解析时间": "2026-05-31T06:13:35.741527"
  },
  {
    "日期": "2026-05-26",
    "品牌": "菜百",
    "产品": "黄金价格",
    "价格": "1370.00",
    "价格_数值": 1370.0,
    "单位": "元/克",
    "纯度": "--",
    "手工费": "另计",
    "涨跌": "--",
    "黄金类型": "实物黄金",
    "黄金类型代码": "physical",
    "数据来源": "新浪财经",
    "解析时间": "2026-05-31T06:13:35.741532"
  },
  {
    "日期": "2026-05-26",
    "品牌": "老庙",
    "产品": "黄金价格",
    "价格": "1386.00",
    "价格_数值": 1386.0,
    "单位": "元/克",
    "纯度": "--",
    "手工费": "另计",
    "涨跌": "跌",
    "黄金类型": "实物黄金",
    "黄金类型代码": "physical",
    "数据来源": "新浪财经",
    "解析时间": "2026-05-31T06:13:35.741534"
  },
  {
    "日期": "2026-05-26",
    "品牌": "金至尊",
    "产品": "黄金价格",
    "价格": "1384.00",
    "价格_数值": 1384.0,
    "单位": "元/克",
    "纯度": "--",
    "手工费": "另计",
    "涨跌": "跌",
    "黄金类型": "实物黄金",
    "黄金类型代码": "physical",
    "数据来源": "新浪财经",
    "解析时间": "2026-05-31T06:13:35.741537"
  },
  {
    "日期": "2026-05-25",
    "品牌": "菜百",
    "产品": "黄金价格",
    "价格": "1370.00",
    "价格_数值": 1370.0,
    "单位": "元/克",
    "纯度": "--",
    "手工费": "另计",
    "涨跌": "--",
    "黄金类型": "实物黄金",
    "黄金类型代码": "physical",
    "数据来源": "新浪财经",
    "解析时间": "2026-05-31T06:13:35.741540"
  },
  {
    "日期": "2026-05-25",
    "品牌": "周生生",
    "产品": "黄金价格",
    "价格": "1396.00",
    "价格_数值": 1396.0,
    "单位": "元/克",
    "纯度": "--",
    "手工费": "另计",
    "涨跌": "涨",
    "黄金类型": "实物黄金",
    "黄金类型代码": "physical",
    "数据来源": "新浪财经",
    "解析时间": "2026-05-31T06:13:35.741543"
  },
  {
    "日期": "2026-05-25",
    "品牌": "周大福",
    "产品": "黄金价格",
    "价格": "1393.00",
    "价格_数值": 1393.0,
    "单位": "元/克",
    "纯度": "--",
    "手工费": "另计",
    "涨跌": "涨",
    "黄金类型": "实物黄金",
    "黄金类型代码": "physical",
    "数据来源": "新浪财经",
    "解析时间": "2026-05-31T06:13:35.741546"
  },
  {
    "日期": "2026-05-25",
    "品牌": "金至尊",
    "产品": "黄金价格",
    "价格": "1391.00",
    "价格_数值": 1391.0,
    "单位": "元/克",
    "纯度": "--",
    "手工费": "另计",
    "涨跌": "涨",
    "黄金类型": "实物黄金",
    "黄金类型代码": "physical",
    "数据来源": "新浪财经",
    "解析时间": "2026-05-31T06:13:35.741549"
  },
  {
    "日期": "2026-05-25",
    "品牌": "六福",
    "产品": "黄金价格",
    "价格": "1391.00",
    "价格_数值": 1391.0,
    "单位": "元/克",
    "纯度": "--",
    "手工费": "另计",
    "涨跌": "涨",
    "黄金类型": "实物黄金",
    "黄金类型代码": "physical",
    "数据来源": "新浪财经",
    "解析时间": "2026-05-31T06:13:35.741552"
  },
  {
    "日期": "2026-05-25",
    "品牌": "老庙",
    "产品": "黄金价格",
    "价格": "1395.00",
    "价格_数值": 1395.0,
    "单位": "元/克",
    "纯度": "--",
    "手工费": "另计",
    "涨跌": "涨",
    "黄金类型": "实物黄金",
    "黄金类型代码": "physical",
    "数据来源": "新浪财经",
    "解析时间": "2026-05-31T06:13:35.741555"
  },
  {
    "日期": "2026-05-23",
    "品牌": "老庙",
    "产品": "黄金价格",
    "价格": "1379.00",
    "价格_数值": 1379.0,
    "单位": "元/克",
    "纯度": "--",
    "手工费": "另计",
    "涨跌": "跌",
    "黄金类型": "实物黄金",
    "黄金类型代码": "physical",
    "数据来源": "新浪财经",
    "解析时间": "2026-05-31T06:13:35.741573"
  },
  {
    "日期": "2026-05-23",
    "品牌": "周大福",
    "产品": "黄金价格",
    "价格": "1380.00",
    "价格_数值": 1380.0,
    "单位": "元/克",
    "纯度": "--",
    "手工费": "另计",
    "涨跌": "--",
    "黄金类型": "实物黄金",
    "黄金类型代码": "physical",
    "数据来源": "新浪财经",
    "解析时间": "2026-05-31T06:13:35.741578"
  },
  {
    "日期": "2026-05-23",
    "品牌": "周生生",
    "产品": "黄金价格",
    "价格": "1376.00",
    "价格_数值": 1376.0,
    "单位": "元/克",
    "纯度": "--",
    "手工费": "另计",
    "涨跌": "跌",
    "黄金类型": "实物黄金",
    "黄金类型代码": "physical",
    "数据来源": "新浪财经",
    "解析时间": "2026-05-31T06:13:35.741581"
  },
  {
    "日期": "2026-05-23",
    "品牌": "六福",
    "产品": "黄金价格",
    "价格": "1378.00",
    "价格_数值": 1378.0,
    "单位": "元/克",
    "纯度": "--",
    "手工费": "另计",
    "涨跌": "--",
    "黄金类型": "实物黄金",
    "黄金类型代码": "physical",
    "数据来源": "新浪财经",
    "解析时间": "2026-05-31T06:13:35.741584"
  },
  {
    "日期": "2026-05-23",
    "品牌": "菜百",
    "产品": "黄金价格",
    "价格": "1370.00",
    "价格_数值": 1370.0,
    "单位": "元/克",
    "纯度": "--",
    "手工费": "另计",
    "涨跌": "--",
    "黄金类型": "实物黄金",
    "黄金类型代码": "physical",
    "数据来源": "新浪财经",
    "解析时间": "2026-05-31T06:13:35.741587"
  },
  {
    "日期": "2026-05-23",
    "品牌": "金至尊",
    "产品": "黄金价格",
    "价格": "1378.00",
    "价格_数值": 1378.0,
    "单位": "元/克",
    "纯度": "--",
    "手工费": "另计",
    "涨跌": "--",
    "黄金类型": "实物黄金",
    "黄金类型代码": "physical",
    "数据来源": "新浪财经",
    "解析时间": "2026-05-31T06:13:35.741590"
  },
  {
    "日期": "2026-05-22",
    "品牌": "老庙",
    "产品": "黄金价格",
    "价格": "1380.00",
    "价格_数值": 1380.0,
    "单位": "元/克",
    "纯度": "--",
    "手工费": "另计",
    "涨跌": "--",
    "黄金类型": "实物黄金",
    "黄金类型代码": "physical",
    "数据来源": "新浪财经",
    "解析时间": "2026-05-31T06:13:35.741593"
  },
  {
    "日期": "2026-05-22",
    "品牌": "六福",
    "产品": "黄金价格",
    "价格": "1378.00",
    "价格_数值": 1378.0,
    "单位": "元/克",
    "纯度": "--",
    "手工费": "另计",
    "涨跌": "--",
    "黄金类型": "实物黄金",
    "黄金类型代码": "physical",
    "数据来源": "新浪财经",
    "解析时间": "2026-05-31T06:13:35.741595"
  },
  {
    "日期": "2026-05-22",
    "品牌": "金至尊",
    "产品": "黄金价格",
    "价格": "1378.00",
    "价格_数值": 1378.0,
    "单位": "元/克",
    "纯度": "--",
    "手工费": "另计",
    "涨跌": "--",
    "黄金类型": "实物黄金",
    "黄金类型代码": "physical",
    "数据来源": "新浪财经",
    "解析时间": "2026-05-31T06:13:35.741598"
  },
  {
    "日期": "2026-05-22",
    "品牌": "菜百",
    "产品": "黄金价格",
    "价格": "1370.00",
    "价格_数值": 1370.0,
    "单位": "元/克",
    "纯度": "--",
    "手工费": "另计",
    "涨跌": "--",
    "黄金类型": "实物黄金",
    "黄金类型代码": "physical",
    "数据来源": "新浪财经",
    "解析时间": "2026-05-31T06:13:35.741601"
  },
  {
    "日期": "2026-05-22",
    "品牌": "周大福",
    "产品": "黄金价格",
    "价格": "1380.00",
    "价格_数值": 1380.0,
    "单位": "元/克",
    "纯度": "--",
    "手工费": "另计",
    "涨跌": "--",
    "黄金类型": "实物黄金",
    "黄金类型代码": "physical",
    "数据来源": "新浪财经",
    "解析时间": "2026-05-31T06:13:35.741604"
  },
  {
    "日期": "2026-05-22",
    "品牌": "周生生",
    "产品": "黄金价格",
    "价格": "1385.00",
    "价格_数值": 1385.0,
    "单位": "元/克",
    "纯度": "--",
    "手工费": "另计",
    "涨跌": "--",
    "黄金类型": "实物黄金",
    "黄金类型代码": "physical",
    "数据来源": "新浪财经",
    "解析时间": "2026-05-31T06:13:35.741607"
  },
  {
    "日期": "2026-05-21",
    "品牌": "周生生",
    "产品": "黄金价格",
    "价格": "1385.00",
    "价格_数值": 1385.0,
    "单位": "元/克",
    "纯度": "--",
    "手工费": "另计",
    "涨跌": "涨",
    "黄金类型": "实物黄金",
    "黄金类型代码": "physical",
    "数据来源": "新浪财经",
    "解析时间": "2026-05-31T06:13:35.741610"
  },
  {
    "日期": "2026-05-21",
    "品牌": "菜百",
    "产品": "黄金价格",
    "价格": "1370.00",
    "价格_数值": 1370.0,
    "单位": "元/克",
    "纯度": "--",
    "手工费": "另计",
    "涨跌": "--",
    "黄金类型": "实物黄金",
    "黄金类型代码": "physical",
    "数据来源": "新浪财经",
    "解析时间": "2026-05-31T06:13:35.741613"
  }
]