[
  {
    "日期": "2026-05-19",
    "品牌": "周生生",
    "产品": "黄金价格",
    "价格": "1391.00",
    "价格_数值": 1391.0,
    "单位": "元/克",
    "纯度": "--",
    "手工费": "另计",
    "涨跌": "涨",
    "黄金类型": "实物黄金",
    "黄金类型代码": "physical",
    "数据来源": "新浪财经",
    "解析时间": "2026-05-19T06:03:16.709826"
  },
  {
    "日期": "2026-05-19",
    "品牌": "六福",
    "产品": "黄金价格",
    "价格": "1394.00",
    "价格_数值": 1394.0,
    "单位": "元/克",
    "纯度": "--",
    "手工费": "另计",
    "涨跌": "涨",
    "黄金类型": "实物黄金",
    "黄金类型代码": "physical",
    "数据来源": "新浪财经",
    "解析时间": "2026-05-19T06:03:16.709839"
  },
  {
    "日期": "2026-05-19",
    "品牌": "金至尊",
    "产品": "黄金价格",
    "价格": "1394.00",
    "价格_数值": 1394.0,
    "单位": "元/克",
    "纯度": "--",
    "手工费": "另计",
    "涨跌": "涨",
    "黄金类型": "实物黄金",
    "黄金类型代码": "physical",
    "数据来源": "新浪财经",
    "解析时间": "2026-05-19T06:03:16.709842"
  },
  {
    "日期": "2026-05-19",
    "品牌": "菜百",
    "产品": "黄金价格",
    "价格": "1382.00",
    "价格_数值": 1382.0,
    "单位": "元/克",
    "纯度": "--",
    "手工费": "另计",
    "涨跌": "--",
    "黄金类型": "实物黄金",
    "黄金类型代码": "physical",
    "数据来源": "新浪财经",
    "解析时间": "2026-05-19T06:03:16.709846"
  },
  {
    "日期": "2026-05-19",
    "品牌": "老庙",
    "产品": "黄金价格",
    "价格": "1397.00",
    "价格_数值": 1397.0,
    "单位": "元/克",
    "纯度": "--",
    "手工费": "另计",
    "涨跌": "涨",
    "黄金类型": "实物黄金",
    "黄金类型代码": "physical",
    "数据来源": "新浪财经",
    "解析时间": "2026-05-19T06:03:16.709849"
  },
  {
    "日期": "2026-05-19",
    "品牌": "周大福",
    "产品": "黄金价格",
    "价格": "1396.00",
    "价格_数值": 1396.0,
    "单位": "元/克",
    "纯度": "--",
    "手工费": "另计",
    "涨跌": "涨",
    "黄金类型": "实物黄金",
    "黄金类型代码": "physical",
    "数据来源": "新浪财经",
    "解析时间": "2026-05-19T06:03:16.709852"
  },
  {
    "日期": "2026-05-18",
    "品牌": "六福",
    "产品": "黄金价格",
    "价格": "1377.00",
    "价格_数值": 1377.0,
    "单位": "元/克",
    "纯度": "--",
    "手工费": "另计",
    "涨跌": "跌",
    "黄金类型": "实物黄金",
    "黄金类型代码": "physical",
    "数据来源": "新浪财经",
    "解析时间": "2026-05-19T06:03:16.709854"
  },
  {
    "日期": "2026-05-18",
    "品牌": "周大福",
    "产品": "黄金价格",
    "价格": "1379.00",
    "价格_数值": 1379.0,
    "单位": "元/克",
    "纯度": "--",
    "手工费": "另计",
    "涨跌": "跌",
    "黄金类型": "实物黄金",
    "黄金类型代码": "physical",
    "数据来源": "新浪财经",
    "解析时间": "2026-05-19T06:03:16.709861"
  },
  {
    "日期": "2026-05-18",
    "品牌": "老庙",
    "产品": "黄金价格",
    "价格": "1379.00",
    "价格_数值": 1379.0,
    "单位": "元/克",
    "纯度": "--",
    "手工费": "另计",
    "涨跌": "跌",
    "黄金类型": "实物黄金",
    "黄金类型代码": "physical",
    "数据来源": "新浪财经",
    "解析时间": "2026-05-19T06:03:16.709864"
  },
  {
    "日期": "2026-05-18",
    "品牌": "菜百",
    "产品": "黄金价格",
    "价格": "1382.00",
    "价格_数值": 1382.0,
    "单位": "元/克",
    "纯度": "--",
    "手工费": "另计",
    "涨跌": "--",
    "黄金类型": "实物黄金",
    "黄金类型代码": "physical",
    "数据来源": "新浪财经",
    "解析时间": "2026-05-19T06:03:16.709867"
  },
  {
    "日期": "2026-05-18",
    "品牌": "周生生",
    "产品": "黄金价格",
    "价格": "1377.00",
    "价格_数值": 1377.0,
    "单位": "元/克",
    "纯度": "--",
    "手工费": "另计",
    "涨跌": "跌",
    "黄金类型": "实物黄金",
    "黄金类型代码": "physical",
    "数据来源": "新浪财经",
    "解析时间": "2026-05-19T06:03:16.709869"
  },
  {
    "日期": "2026-05-18",
    "品牌": "金至尊",
    "产品": "黄金价格",
    "价格": "1377.00",
    "价格_数值": 1377.0,
    "单位": "元/克",
    "纯度": "--",
    "手工费": "另计",
    "涨跌": "跌",
    "黄金类型": "实物黄金",
    "黄金类型代码": "physical",
    "数据来源": "新浪财经",
    "解析时间": "2026-05-19T06:03:16.709872"
  },
  {
    "日期": "2026-05-16",
    "品牌": "菜百",
    "产品": "黄金价格",
    "价格": "1382.00",
    "价格_数值": 1382.0,
    "单位": "元/克",
    "纯度": "--",
    "手工费": "另计",
    "涨跌": "跌",
    "黄金类型": "实物黄金",
    "黄金类型代码": "physical",
    "数据来源": "新浪财经",
    "解析时间": "2026-05-19T06:03:16.709875"
  },
  {
    "日期": "2026-05-16",
    "品牌": "老庙",
    "产品": "黄金价格",
    "价格": "1396.00",
    "价格_数值": 1396.0,
    "单位": "元/克",
    "纯度": "--",
    "手工费": "另计",
    "涨跌": "跌",
    "黄金类型": "实物黄金",
    "黄金类型代码": "physical",
    "数据来源": "新浪财经",
    "解析时间": "2026-05-19T06:03:16.709878"
  },
  {
    "日期": "2026-05-16",
    "品牌": "六福",
    "产品": "黄金价格",
    "价格": "1391.00",
    "价格_数值": 1391.0,
    "单位": "元/克",
    "纯度": "--",
    "手工费": "另计",
    "涨跌": "跌",
    "黄金类型": "实物黄金",
    "黄金类型代码": "physical",
    "数据来源": "新浪财经",
    "解析时间": "2026-05-19T06:03:16.709881"
  },
  {
    "日期": "2026-05-16",
    "品牌": "金至尊",
    "产品": "黄金价格",
    "价格": "1391.00",
    "价格_数值": 1391.0,
    "单位": "元/克",
    "纯度": "--",
    "手工费": "另计",
    "涨跌": "跌",
    "黄金类型": "实物黄金",
    "黄金类型代码": "physical",
    "数据来源": "新浪财经",
    "解析时间": "2026-05-19T06:03:16.709883"
  },
  {
    "日期": "2026-05-16",
    "品牌": "周生生",
    "产品": "黄金价格",
    "价格": "1390.00",
    "价格_数值": 1390.0,
    "单位": "元/克",
    "纯度": "--",
    "手工费": "另计",
    "涨跌": "跌",
    "黄金类型": "实物黄金",
    "黄金类型代码": "physical",
    "数据来源": "新浪财经",
    "解析时间": "2026-05-19T06:03:16.709886"
  },
  {
    "日期": "2026-05-16",
    "品牌": "周大福",
    "产品": "黄金价格",
    "价格": "1393.00",
    "价格_数值": 1393.0,
    "单位": "元/克",
    "纯度": "--",
    "手工费": "另计",
    "涨跌": "跌",
    "黄金类型": "实物黄金",
    "黄金类型代码": "physical",
    "数据来源": "新浪财经",
    "解析时间": "2026-05-19T06:03:16.709890"
  },
  {
    "日期": "2026-05-15",
    "品牌": "老庙",
    "产品": "黄金价格",
    "价格": "1411.00",
    "价格_数值": 1411.0,
    "单位": "元/克",
    "纯度": "--",
    "手工费": "另计",
    "涨跌": "跌",
    "黄金类型": "实物黄金",
    "黄金类型代码": "physical",
    "数据来源": "新浪财经",
    "解析时间": "2026-05-19T06:03:16.709893"
  },
  {
    "日期": "2026-05-15",
    "品牌": "六福",
    "产品": "黄金价格",
    "价格": "1406.00",
    "价格_数值": 1406.0,
    "单位": "元/克",
    "纯度": "--",
    "手工费": "另计",
    "涨跌": "跌",
    "黄金类型": "实物黄金",
    "黄金类型代码": "physical",
    "数据来源": "新浪财经",
    "解析时间": "2026-05-19T06:03:16.709896"
  },
  {
    "日期": "2026-05-15",
    "品牌": "金至尊",
    "产品": "黄金价格",
    "价格": "1406.00",
    "价格_数值": 1406.0,
    "单位": "元/克",
    "纯度": "--",
    "手工费": "另计",
    "涨跌": "跌",
    "黄金类型": "实物黄金",
    "黄金类型代码": "physical",
    "数据来源": "新浪财经",
    "解析时间": "2026-05-19T06:03:16.709899"
  },
  {
    "日期": "2026-05-15",
    "品牌": "周生生",
    "产品": "黄金价格",
    "价格": "1402.00",
    "价格_数值": 1402.0,
    "单位": "元/克",
    "纯度": "--",
    "手工费": "另计",
    "涨跌": "跌",
    "黄金类型": "实物黄金",
    "黄金类型代码": "physical",
    "数据来源": "新浪财经",
    "解析时间": "2026-05-19T06:03:16.709901"
  },
  {
    "日期": "2026-05-15",
    "品牌": "周大福",
    "产品": "黄金价格",
    "价格": "1408.00",
    "价格_数值": 1408.0,
    "单位": "元/克",
    "纯度": "--",
    "手工费": "另计",
    "涨跌": "跌",
    "黄金类型": "实物黄金",
    "黄金类型代码": "physical",
    "数据来源": "新浪财经",
    "解析时间": "2026-05-19T06:03:16.709904"
  },
  {
    "日期": "2026-05-15",
    "品牌": "菜百",
    "产品": "黄金价格",
    "价格": "1405.00",
    "价格_数值": 1405.0,
    "单位": "元/克",
    "纯度": "--",
    "手工费": "另计",
    "涨跌": "跌",
    "黄金类型": "实物黄金",
    "黄金类型代码": "physical",
    "数据来源": "新浪财经",
    "解析时间": "2026-05-19T06:03:16.709907"
  },
  {
    "日期": "2026-05-14",
    "品牌": "周大福",
    "产品": "黄金价格",
    "价格": "1428.00",
    "价格_数值": 1428.0,
    "单位": "元/克",
    "纯度": "--",
    "手工费": "另计",
    "涨跌": "跌",
    "黄金类型": "实物黄金",
    "黄金类型代码": "physical",
    "数据来源": "新浪财经",
    "解析时间": "2026-05-19T06:03:16.709910"
  },
  {
    "日期": "2026-05-14",
    "品牌": "周生生",
    "产品": "黄金价格",
    "价格": "1430.00",
    "价格_数值": 1430.0,
    "单位": "元/克",
    "纯度": "--",
    "手工费": "另计",
    "涨跌": "跌",
    "黄金类型": "实物黄金",
    "黄金类型代码": "physical",
    "数据来源": "新浪财经",
    "解析时间": "2026-05-19T06:03:16.709913"
  },
  {
    "日期": "2026-05-14",
    "品牌": "六福",
    "产品": "黄金价格",
    "价格": "1426.00",
    "价格_数值": 1426.0,
    "单位": "元/克",
    "纯度": "--",
    "手工费": "另计",
    "涨跌": "跌",
    "黄金类型": "实物黄金",
    "黄金类型代码": "physical",
    "数据来源": "新浪财经",
    "解析时间": "2026-05-19T06:03:16.709915"
  },
  {
    "日期": "2026-05-14",
    "品牌": "菜百",
    "产品": "黄金价格",
    "价格": "1415.00",
    "价格_数值": 1415.0,
    "单位": "元/克",
    "纯度": "--",
    "手工费": "另计",
    "涨跌": "--",
    "黄金类型": "实物黄金",
    "黄金类型代码": "physical",
    "数据来源": "新浪财经",
    "解析时间": "2026-05-19T06:03:16.709920"
  },
  {
    "日期": "2026-05-14",
    "品牌": "老庙",
    "产品": "黄金价格",
    "价格": "1428.00",
    "价格_数值": 1428.0,
    "单位": "元/克",
    "纯度": "--",
    "手工费": "另计",
    "涨跌": "跌",
    "黄金类型": "实物黄金",
    "黄金类型代码": "physical",
    "数据来源": "新浪财经",
    "解析时间": "2026-05-19T06:03:16.709922"
  },
  {
    "日期": "2026-05-14",
    "品牌": "金至尊",
    "产品": "黄金价格",
    "价格": "1426.00",
    "价格_数值": 1426.0,
    "单位": "元/克",
    "纯度": "--",
    "手工费": "另计",
    "涨跌": "跌",
    "黄金类型": "实物黄金",
    "黄金类型代码": "physical",
    "数据来源": "新浪财经",
    "解析时间": "2026-05-19T06:03:16.709925"
  },
  {
    "日期": "2026-05-13",
    "品牌": "菜百",
    "产品": "黄金价格",
    "价格": "1415.00",
    "价格_数值": 1415.0,
    "单位": "元/克",
    "纯度": "--",
    "手工费": "另计",
    "涨跌": "--",
    "黄金类型": "实物黄金",
    "黄金类型代码": "physical",
    "数据来源": "新浪财经",
    "解析时间": "2026-05-19T06:03:16.709928"
  },
  {
    "日期": "2026-05-13",
    "品牌": "周生生",
    "产品": "黄金价格",
    "价格": "1433.00",
    "价格_数值": 1433.0,
    "单位": "元/克",
    "纯度": "--",
    "手工费": "另计",
    "涨跌": "跌",
    "黄金类型": "实物黄金",
    "黄金类型代码": "physical",
    "数据来源": "新浪财经",
    "解析时间": "2026-05-19T06:03:16.709931"
  },
  {
    "日期": "2026-05-13",
    "品牌": "周大福",
    "产品": "黄金价格",
    "价格": "1435.00",
    "价格_数值": 1435.0,
    "单位": "元/克",
    "纯度": "--",
    "手工费": "另计",
    "涨跌": "跌",
    "黄金类型": "实物黄金",
    "黄金类型代码": "physical",
    "数据来源": "新浪财经",
    "解析时间": "2026-05-19T06:03:16.709933"
  },
  {
    "日期": "2026-05-13",
    "品牌": "金至尊",
    "产品": "黄金价格",
    "价格": "1433.00",
    "价格_数值": 1433.0,
    "单位": "元/克",
    "纯度": "--",
    "手工费": "另计",
    "涨跌": "跌",
    "黄金类型": "实物黄金",
    "黄金类型代码": "physical",
    "数据来源": "新浪财经",
    "解析时间": "2026-05-19T06:03:16.709936"
  },
  {
    "日期": "2026-05-13",
    "品牌": "六福",
    "产品": "黄金价格",
    "价格": "1433.00",
    "价格_数值": 1433.0,
    "单位": "元/克",
    "纯度": "--",
    "手工费": "另计",
    "涨跌": "跌",
    "黄金类型": "实物黄金",
    "黄金类型代码": "physical",
    "数据来源": "新浪财经",
    "解析时间": "2026-05-19T06:03:16.709939"
  },
  {
    "日期": "2026-05-13",
    "品牌": "老庙",
    "产品": "黄金价格",
    "价格": "1436.00",
    "价格_数值": 1436.0,
    "单位": "元/克",
    "纯度": "--",
    "手工费": "另计",
    "涨跌": "跌",
    "黄金类型": "实物黄金",
    "黄金类型代码": "physical",
    "数据来源": "新浪财经",
    "解析时间": "2026-05-19T06:03:16.709942"
  },
  {
    "日期": "2026-05-12",
    "品牌": "老庙",
    "产品": "黄金价格",
    "价格": "1441.00",
    "价格_数值": 1441.0,
    "单位": "元/克",
    "纯度": "--",
    "手工费": "另计",
    "涨跌": "涨",
    "黄金类型": "实物黄金",
    "黄金类型代码": "physical",
    "数据来源": "新浪财经",
    "解析时间": "2026-05-19T06:03:16.709945"
  },
  {
    "日期": "2026-05-12",
    "品牌": "周大福",
    "产品": "黄金价格",
    "价格": "1446.00",
    "价格_数值": 1446.0,
    "单位": "元/克",
    "纯度": "--",
    "手工费": "另计",
    "涨跌": "涨",
    "黄金类型": "实物黄金",
    "黄金类型代码": "physical",
    "数据来源": "新浪财经",
    "解析时间": "2026-05-19T06:03:16.709948"
  },
  {
    "日期": "2026-05-12",
    "品牌": "周生生",
    "产品": "黄金价格",
    "价格": "1444.00",
    "价格_数值": 1444.0,
    "单位": "元/克",
    "纯度": "--",
    "手工费": "另计",
    "涨跌": "涨",
    "黄金类型": "实物黄金",
    "黄金类型代码": "physical",
    "数据来源": "新浪财经",
    "解析时间": "2026-05-19T06:03:16.709950"
  },
  {
    "日期": "2026-05-12",
    "品牌": "六福",
    "产品": "黄金价格",
    "价格": "1444.00",
    "价格_数值": 1444.0,
    "单位": "元/克",
    "纯度": "--",
    "手工费": "另计",
    "涨跌": "涨",
    "黄金类型": "实物黄金",
    "黄金类型代码": "physical",
    "数据来源": "新浪财经",
    "解析时间": "2026-05-19T06:03:16.709954"
  },
  {
    "日期": "2026-05-12",
    "品牌": "菜百",
    "产品": "黄金价格",
    "价格": "1415.00",
    "价格_数值": 1415.0,
    "单位": "元/克",
    "纯度": "--",
    "手工费": "另计",
    "涨跌": "涨",
    "黄金类型": "实物黄金",
    "黄金类型代码": "physical",
    "数据来源": "新浪财经",
    "解析时间": "2026-05-19T06:03:16.709956"
  },
  {
    "日期": "2026-05-12",
    "品牌": "金至尊",
    "产品": "黄金价格",
    "价格": "1444.00",
    "价格_数值": 1444.0,
    "单位": "元/克",
    "纯度": "--",
    "手工费": "另计",
    "涨跌": "涨",
    "黄金类型": "实物黄金",
    "黄金类型代码": "physical",
    "数据来源": "新浪财经",
    "解析时间": "2026-05-19T06:03:16.709959"
  },
  {
    "日期": "2026-05-11",
    "品牌": "老庙",
    "产品": "黄金价格",
    "价格": "1429.00",
    "价格_数值": 1429.0,
    "单位": "元/克",
    "纯度": "--",
    "手工费": "另计",
    "涨跌": "跌",
    "黄金类型": "实物黄金",
    "黄金类型代码": "physical",
    "数据来源": "新浪财经",
    "解析时间": "2026-05-19T06:03:16.709962"
  },
  {
    "日期": "2026-05-11",
    "品牌": "六福",
    "产品": "黄金价格",
    "价格": "1435.00",
    "价格_数值": 1435.0,
    "单位": "元/克",
    "纯度": "--",
    "手工费": "另计",
    "涨跌": "--",
    "黄金类型": "实物黄金",
    "黄金类型代码": "physical",
    "数据来源": "新浪财经",
    "解析时间": "2026-05-19T06:03:16.709965"
  },
  {
    "日期": "2026-05-11",
    "品牌": "金至尊",
    "产品": "黄金价格",
    "价格": "1435.00",
    "价格_数值": 1435.0,
    "单位": "元/克",
    "纯度": "--",
    "手工费": "另计",
    "涨跌": "--",
    "黄金类型": "实物黄金",
    "黄金类型代码": "physical",
    "数据来源": "新浪财经",
    "解析时间": "2026-05-19T06:03:16.709968"
  },
  {
    "日期": "2026-05-11",
    "品牌": "菜百",
    "产品": "黄金价格",
    "价格": "1405.00",
    "价格_数值": 1405.0,
    "单位": "元/克",
    "纯度": "--",
    "手工费": "另计",
    "涨跌": "--",
    "黄金类型": "实物黄金",
    "黄金类型代码": "physical",
    "数据来源": "新浪财经",
    "解析时间": "2026-05-19T06:03:16.709970"
  },
  {
    "日期": "2026-05-11",
    "品牌": "周大福",
    "产品": "黄金价格",
    "价格": "1437.00",
    "价格_数值": 1437.0,
    "单位": "元/克",
    "纯度": "--",
    "手工费": "另计",
    "涨跌": "--",
    "黄金类型": "实物黄金",
    "黄金类型代码": "physical",
    "数据来源": "新浪财经",
    "解析时间": "2026-05-19T06:03:16.709973"
  },
  {
    "日期": "2026-05-11",
    "品牌": "周生生",
    "产品": "黄金价格",
    "价格": "1434.00",
    "价格_数值": 1434.0,
    "单位": "元/克",
    "纯度": "--",
    "手工费": "另计",
    "涨跌": "跌",
    "黄金类型": "实物黄金",
    "黄金类型代码": "physical",
    "数据来源": "新浪财经",
    "解析时间": "2026-05-19T06:03:16.709976"
  },
  {
    "日期": "2026-05-09",
    "品牌": "周生生",
    "产品": "黄金价格",
    "价格": "1438.00",
    "价格_数值": 1438.0,
    "单位": "元/克",
    "纯度": "--",
    "手工费": "另计",
    "涨跌": "--",
    "黄金类型": "实物黄金",
    "黄金类型代码": "physical",
    "数据来源": "新浪财经",
    "解析时间": "2026-05-19T06:03:16.709979"
  },
  {
    "日期": "2026-05-09",
    "品牌": "菜百",
    "产品": "黄金价格",
    "价格": "1405.00",
    "价格_数值": 1405.0,
    "单位": "元/克",
    "纯度": "--",
    "手工费": "另计",
    "涨跌": "--",
    "黄金类型": "实物黄金",
    "黄金类型代码": "physical",
    "数据来源": "新浪财经",
    "解析时间": "2026-05-19T06:03:16.709981"
  }
]