[
  {
    "日期": "2026-03-20",
    "品牌": "周生生",
    "产品": "黄金价格",
    "价格": "1443.00",
    "价格_数值": 1443.0,
    "单位": "元/克",
    "纯度": "--",
    "手工费": "另计",
    "涨跌": "跌",
    "黄金类型": "实物黄金",
    "黄金类型代码": "physical",
    "数据来源": "新浪财经",
    "解析时间": "2026-03-20T04:10:45.580718"
  },
  {
    "日期": "2026-03-20",
    "品牌": "菜百",
    "产品": "黄金价格",
    "价格": "1478.00",
    "价格_数值": 1478.0,
    "单位": "元/克",
    "纯度": "--",
    "手工费": "另计",
    "涨跌": "跌",
    "黄金类型": "实物黄金",
    "黄金类型代码": "physical",
    "数据来源": "新浪财经",
    "解析时间": "2026-03-20T04:10:45.580732"
  },
  {
    "日期": "2026-03-20",
    "品牌": "周大福",
    "产品": "黄金价格",
    "价格": "1447.00",
    "价格_数值": 1447.0,
    "单位": "元/克",
    "纯度": "--",
    "手工费": "另计",
    "涨跌": "跌",
    "黄金类型": "实物黄金",
    "黄金类型代码": "physical",
    "数据来源": "新浪财经",
    "解析时间": "2026-03-20T04:10:45.580736"
  },
  {
    "日期": "2026-03-20",
    "品牌": "六福",
    "产品": "黄金价格",
    "价格": "1445.00",
    "价格_数值": 1445.0,
    "单位": "元/克",
    "纯度": "--",
    "手工费": "另计",
    "涨跌": "跌",
    "黄金类型": "实物黄金",
    "黄金类型代码": "physical",
    "数据来源": "新浪财经",
    "解析时间": "2026-03-20T04:10:45.580740"
  },
  {
    "日期": "2026-03-20",
    "品牌": "金至尊",
    "产品": "黄金价格",
    "价格": "1445.00",
    "价格_数值": 1445.0,
    "单位": "元/克",
    "纯度": "--",
    "手工费": "另计",
    "涨跌": "跌",
    "黄金类型": "实物黄金",
    "黄金类型代码": "physical",
    "数据来源": "新浪财经",
    "解析时间": "2026-03-20T04:10:45.580743"
  },
  {
    "日期": "2026-03-20",
    "品牌": "老庙",
    "产品": "黄金价格",
    "价格": "1445.00",
    "价格_数值": 1445.0,
    "单位": "元/克",
    "纯度": "--",
    "手工费": "另计",
    "涨跌": "跌",
    "黄金类型": "实物黄金",
    "黄金类型代码": "physical",
    "数据来源": "新浪财经",
    "解析时间": "2026-03-20T04:10:45.580746"
  },
  {
    "日期": "2026-03-19",
    "品牌": "周生生",
    "产品": "黄金价格",
    "价格": "1492.00",
    "价格_数值": 1492.0,
    "单位": "元/克",
    "纯度": "--",
    "手工费": "另计",
    "涨跌": "跌",
    "黄金类型": "实物黄金",
    "黄金类型代码": "physical",
    "数据来源": "新浪财经",
    "解析时间": "2026-03-20T04:10:45.580749"
  },
  {
    "日期": "2026-03-19",
    "品牌": "金至尊",
    "产品": "黄金价格",
    "价格": "1501.00",
    "价格_数值": 1501.0,
    "单位": "元/克",
    "纯度": "--",
    "手工费": "另计",
    "涨跌": "跌",
    "黄金类型": "实物黄金",
    "黄金类型代码": "physical",
    "数据来源": "新浪财经",
    "解析时间": "2026-03-20T04:10:45.580752"
  },
  {
    "日期": "2026-03-19",
    "品牌": "六福",
    "产品": "黄金价格",
    "价格": "1501.00",
    "价格_数值": 1501.0,
    "单位": "元/克",
    "纯度": "--",
    "手工费": "另计",
    "涨跌": "跌",
    "黄金类型": "实物黄金",
    "黄金类型代码": "physical",
    "数据来源": "新浪财经",
    "解析时间": "2026-03-20T04:10:45.580755"
  },
  {
    "日期": "2026-03-19",
    "品牌": "周大福",
    "产品": "黄金价格",
    "价格": "1503.00",
    "价格_数值": 1503.0,
    "单位": "元/克",
    "纯度": "--",
    "手工费": "另计",
    "涨跌": "跌",
    "黄金类型": "实物黄金",
    "黄金类型代码": "physical",
    "数据来源": "新浪财经",
    "解析时间": "2026-03-20T04:10:45.580758"
  },
  {
    "日期": "2026-03-19",
    "品牌": "菜百",
    "产品": "黄金价格",
    "价格": "1495.00",
    "价格_数值": 1495.0,
    "单位": "元/克",
    "纯度": "--",
    "手工费": "另计",
    "涨跌": "跌",
    "黄金类型": "实物黄金",
    "黄金类型代码": "physical",
    "数据来源": "新浪财经",
    "解析时间": "2026-03-20T04:10:45.580761"
  },
  {
    "日期": "2026-03-19",
    "品牌": "老庙",
    "产品": "黄金价格",
    "价格": "1498.00",
    "价格_数值": 1498.0,
    "单位": "元/克",
    "纯度": "--",
    "手工费": "另计",
    "涨跌": "跌",
    "黄金类型": "实物黄金",
    "黄金类型代码": "physical",
    "数据来源": "新浪财经",
    "解析时间": "2026-03-20T04:10:45.580764"
  },
  {
    "日期": "2026-03-18",
    "品牌": "六福",
    "产品": "黄金价格",
    "价格": "1549.00",
    "价格_数值": 1549.0,
    "单位": "元/克",
    "纯度": "--",
    "手工费": "另计",
    "涨跌": "--",
    "黄金类型": "实物黄金",
    "黄金类型代码": "physical",
    "数据来源": "新浪财经",
    "解析时间": "2026-03-20T04:10:45.580767"
  },
  {
    "日期": "2026-03-18",
    "品牌": "金至尊",
    "产品": "黄金价格",
    "价格": "1549.00",
    "价格_数值": 1549.0,
    "单位": "元/克",
    "纯度": "--",
    "手工费": "另计",
    "涨跌": "--",
    "黄金类型": "实物黄金",
    "黄金类型代码": "physical",
    "数据来源": "新浪财经",
    "解析时间": "2026-03-20T04:10:45.580770"
  },
  {
    "日期": "2026-03-18",
    "品牌": "菜百",
    "产品": "黄金价格",
    "价格": "1530.00",
    "价格_数值": 1530.0,
    "单位": "元/克",
    "纯度": "--",
    "手工费": "另计",
    "涨跌": "--",
    "黄金类型": "实物黄金",
    "黄金类型代码": "physical",
    "数据来源": "新浪财经",
    "解析时间": "2026-03-20T04:10:45.580773"
  },
  {
    "日期": "2026-03-18",
    "品牌": "周生生",
    "产品": "黄金价格",
    "价格": "1547.00",
    "价格_数值": 1547.0,
    "单位": "元/克",
    "纯度": "--",
    "手工费": "另计",
    "涨跌": "跌",
    "黄金类型": "实物黄金",
    "黄金类型代码": "physical",
    "数据来源": "新浪财经",
    "解析时间": "2026-03-20T04:10:45.580775"
  },
  {
    "日期": "2026-03-18",
    "品牌": "老庙",
    "产品": "黄金价格",
    "价格": "1550.00",
    "价格_数值": 1550.0,
    "单位": "元/克",
    "纯度": "--",
    "手工费": "另计",
    "涨跌": "跌",
    "黄金类型": "实物黄金",
    "黄金类型代码": "physical",
    "数据来源": "新浪财经",
    "解析时间": "2026-03-20T04:10:45.580778"
  },
  {
    "日期": "2026-03-18",
    "品牌": "周大福",
    "产品": "黄金价格",
    "价格": "1551.00",
    "价格_数值": 1551.0,
    "单位": "元/克",
    "纯度": "--",
    "手工费": "另计",
    "涨跌": "--",
    "黄金类型": "实物黄金",
    "黄金类型代码": "physical",
    "数据来源": "新浪财经",
    "解析时间": "2026-03-20T04:10:45.580781"
  },
  {
    "日期": "2026-03-17",
    "品牌": "菜百",
    "产品": "黄金价格",
    "价格": "1530.00",
    "价格_数值": 1530.0,
    "单位": "元/克",
    "纯度": "--",
    "手工费": "另计",
    "涨跌": "--",
    "黄金类型": "实物黄金",
    "黄金类型代码": "physical",
    "数据来源": "新浪财经",
    "解析时间": "2026-03-20T04:10:45.580784"
  },
  {
    "日期": "2026-03-17",
    "品牌": "六福",
    "产品": "黄金价格",
    "价格": "1549.00",
    "价格_数值": 1549.0,
    "单位": "元/克",
    "纯度": "--",
    "手工费": "另计",
    "涨跌": "跌",
    "黄金类型": "实物黄金",
    "黄金类型代码": "physical",
    "数据来源": "新浪财经",
    "解析时间": "2026-03-20T04:10:45.580787"
  },
  {
    "日期": "2026-03-17",
    "品牌": "周大福",
    "产品": "黄金价格",
    "价格": "1551.00",
    "价格_数值": 1551.0,
    "单位": "元/克",
    "纯度": "--",
    "手工费": "另计",
    "涨跌": "跌",
    "黄金类型": "实物黄金",
    "黄金类型代码": "physical",
    "数据来源": "新浪财经",
    "解析时间": "2026-03-20T04:10:45.580789"
  },
  {
    "日期": "2026-03-17",
    "品牌": "老庙",
    "产品": "黄金价格",
    "价格": "1552.00",
    "价格_数值": 1552.0,
    "单位": "元/克",
    "纯度": "--",
    "手工费": "另计",
    "涨跌": "跌",
    "黄金类型": "实物黄金",
    "黄金类型代码": "physical",
    "数据来源": "新浪财经",
    "解析时间": "2026-03-20T04:10:45.580792"
  },
  {
    "日期": "2026-03-17",
    "品牌": "周生生",
    "产品": "黄金价格",
    "价格": "1550.00",
    "价格_数值": 1550.0,
    "单位": "元/克",
    "纯度": "--",
    "手工费": "另计",
    "涨跌": "--",
    "黄金类型": "实物黄金",
    "黄金类型代码": "physical",
    "数据来源": "新浪财经",
    "解析时间": "2026-03-20T04:10:45.580795"
  },
  {
    "日期": "2026-03-17",
    "品牌": "金至尊",
    "产品": "黄金价格",
    "价格": "1549.00",
    "价格_数值": 1549.0,
    "单位": "元/克",
    "纯度": "--",
    "手工费": "另计",
    "涨跌": "跌",
    "黄金类型": "实物黄金",
    "黄金类型代码": "physical",
    "数据来源": "新浪财经",
    "解析时间": "2026-03-20T04:10:45.580798"
  },
  {
    "日期": "2026-03-16",
    "品牌": "金至尊",
    "产品": "黄金价格",
    "价格": "1555.00",
    "价格_数值": 1555.0,
    "单位": "元/克",
    "纯度": "--",
    "手工费": "另计",
    "涨跌": "--",
    "黄金类型": "实物黄金",
    "黄金类型代码": "physical",
    "数据来源": "新浪财经",
    "解析时间": "2026-03-20T04:10:45.580800"
  },
  {
    "日期": "2026-03-16",
    "品牌": "菜百",
    "产品": "黄金价格",
    "价格": "1530.00",
    "价格_数值": 1530.0,
    "单位": "元/克",
    "纯度": "--",
    "手工费": "另计",
    "涨跌": "--",
    "黄金类型": "实物黄金",
    "黄金类型代码": "physical",
    "数据来源": "新浪财经",
    "解析时间": "2026-03-20T04:10:45.580803"
  },
  {
    "日期": "2026-03-16",
    "品牌": "周生生",
    "产品": "黄金价格",
    "价格": "1550.00",
    "价格_数值": 1550.0,
    "单位": "元/克",
    "纯度": "--",
    "手工费": "另计",
    "涨跌": "涨",
    "黄金类型": "实物黄金",
    "黄金类型代码": "physical",
    "数据来源": "新浪财经",
    "解析时间": "2026-03-20T04:10:45.580806"
  },
  {
    "日期": "2026-03-16",
    "品牌": "老庙",
    "产品": "黄金价格",
    "价格": "1560.00",
    "价格_数值": 1560.0,
    "单位": "元/克",
    "纯度": "--",
    "手工费": "另计",
    "涨跌": "跌",
    "黄金类型": "实物黄金",
    "黄金类型代码": "physical",
    "数据来源": "新浪财经",
    "解析时间": "2026-03-20T04:10:45.580809"
  },
  {
    "日期": "2026-03-16",
    "品牌": "六福",
    "产品": "黄金价格",
    "价格": "1555.00",
    "价格_数值": 1555.0,
    "单位": "元/克",
    "纯度": "--",
    "手工费": "另计",
    "涨跌": "--",
    "黄金类型": "实物黄金",
    "黄金类型代码": "physical",
    "数据来源": "新浪财经",
    "解析时间": "2026-03-20T04:10:45.580812"
  },
  {
    "日期": "2026-03-16",
    "品牌": "周大福",
    "产品": "黄金价格",
    "价格": "1557.00",
    "价格_数值": 1557.0,
    "单位": "元/克",
    "纯度": "--",
    "手工费": "另计",
    "涨跌": "--",
    "黄金类型": "实物黄金",
    "黄金类型代码": "physical",
    "数据来源": "新浪财经",
    "解析时间": "2026-03-20T04:10:45.580814"
  },
  {
    "日期": "2026-03-14",
    "品牌": "六福",
    "产品": "黄金价格",
    "价格": "1555.00",
    "价格_数值": 1555.0,
    "单位": "元/克",
    "纯度": "--",
    "手工费": "另计",
    "涨跌": "跌",
    "黄金类型": "实物黄金",
    "黄金类型代码": "physical",
    "数据来源": "新浪财经",
    "解析时间": "2026-03-20T04:10:45.580817"
  },
  {
    "日期": "2026-03-14",
    "品牌": "老庙",
    "产品": "黄金价格",
    "价格": "1565.00",
    "价格_数值": 1565.0,
    "单位": "元/克",
    "纯度": "--",
    "手工费": "另计",
    "涨跌": "跌",
    "黄金类型": "实物黄金",
    "黄金类型代码": "physical",
    "数据来源": "新浪财经",
    "解析时间": "2026-03-20T04:10:45.580820"
  },
  {
    "日期": "2026-03-14",
    "品牌": "周大福",
    "产品": "黄金价格",
    "价格": "1557.00",
    "价格_数值": 1557.0,
    "单位": "元/克",
    "纯度": "--",
    "手工费": "另计",
    "涨跌": "跌",
    "黄金类型": "实物黄金",
    "黄金类型代码": "physical",
    "数据来源": "新浪财经",
    "解析时间": "2026-03-20T04:10:45.580823"
  },
  {
    "日期": "2026-03-14",
    "品牌": "周生生",
    "产品": "黄金价格",
    "价格": "1547.00",
    "价格_数值": 1547.0,
    "单位": "元/克",
    "纯度": "--",
    "手工费": "另计",
    "涨跌": "跌",
    "黄金类型": "实物黄金",
    "黄金类型代码": "physical",
    "数据来源": "新浪财经",
    "解析时间": "2026-03-20T04:10:45.580826"
  },
  {
    "日期": "2026-03-14",
    "品牌": "金至尊",
    "产品": "黄金价格",
    "价格": "1555.00",
    "价格_数值": 1555.0,
    "单位": "元/克",
    "纯度": "--",
    "手工费": "另计",
    "涨跌": "跌",
    "黄金类型": "实物黄金",
    "黄金类型代码": "physical",
    "数据来源": "新浪财经",
    "解析时间": "2026-03-20T04:10:45.580828"
  },
  {
    "日期": "2026-03-14",
    "品牌": "菜百",
    "产品": "黄金价格",
    "价格": "1530.00",
    "价格_数值": 1530.0,
    "单位": "元/克",
    "纯度": "--",
    "手工费": "另计",
    "涨跌": "跌",
    "黄金类型": "实物黄金",
    "黄金类型代码": "physical",
    "数据来源": "新浪财经",
    "解析时间": "2026-03-20T04:10:45.580831"
  },
  {
    "日期": "2026-03-13",
    "品牌": "老庙",
    "产品": "黄金价格",
    "价格": "1570.00",
    "价格_数值": 1570.0,
    "单位": "元/克",
    "纯度": "--",
    "手工费": "另计",
    "涨跌": "跌",
    "黄金类型": "实物黄金",
    "黄金类型代码": "physical",
    "数据来源": "新浪财经",
    "解析时间": "2026-03-20T04:10:45.580834"
  },
  {
    "日期": "2026-03-13",
    "品牌": "金至尊",
    "产品": "黄金价格",
    "价格": "1578.00",
    "价格_数值": 1578.0,
    "单位": "元/克",
    "纯度": "--",
    "手工费": "另计",
    "涨跌": "跌",
    "黄金类型": "实物黄金",
    "黄金类型代码": "physical",
    "数据来源": "新浪财经",
    "解析时间": "2026-03-20T04:10:45.580836"
  },
  {
    "日期": "2026-03-13",
    "品牌": "六福",
    "产品": "黄金价格",
    "价格": "1578.00",
    "价格_数值": 1578.0,
    "单位": "元/克",
    "纯度": "--",
    "手工费": "另计",
    "涨跌": "跌",
    "黄金类型": "实物黄金",
    "黄金类型代码": "physical",
    "数据来源": "新浪财经",
    "解析时间": "2026-03-20T04:10:45.580839"
  },
  {
    "日期": "2026-03-13",
    "品牌": "周大福",
    "产品": "黄金价格",
    "价格": "1580.00",
    "价格_数值": 1580.0,
    "单位": "元/克",
    "纯度": "--",
    "手工费": "另计",
    "涨跌": "跌",
    "黄金类型": "实物黄金",
    "黄金类型代码": "physical",
    "数据来源": "新浪财经",
    "解析时间": "2026-03-20T04:10:45.580842"
  },
  {
    "日期": "2026-03-13",
    "品牌": "菜百",
    "产品": "黄金价格",
    "价格": "1538.00",
    "价格_数值": 1538.0,
    "单位": "元/克",
    "纯度": "--",
    "手工费": "另计",
    "涨跌": "跌",
    "黄金类型": "实物黄金",
    "黄金类型代码": "physical",
    "数据来源": "新浪财经",
    "解析时间": "2026-03-20T04:10:45.580845"
  },
  {
    "日期": "2026-03-13",
    "品牌": "周生生",
    "产品": "黄金价格",
    "价格": "1572.00",
    "价格_数值": 1572.0,
    "单位": "元/克",
    "纯度": "--",
    "手工费": "另计",
    "涨跌": "跌",
    "黄金类型": "实物黄金",
    "黄金类型代码": "physical",
    "数据来源": "新浪财经",
    "解析时间": "2026-03-20T04:10:45.580847"
  },
  {
    "日期": "2026-03-12",
    "品牌": "金至尊",
    "产品": "黄金价格",
    "价格": "1584.00",
    "价格_数值": 1584.0,
    "单位": "元/克",
    "纯度": "--",
    "手工费": "另计",
    "涨跌": "跌",
    "黄金类型": "实物黄金",
    "黄金类型代码": "physical",
    "数据来源": "新浪财经",
    "解析时间": "2026-03-20T04:10:45.580850"
  },
  {
    "日期": "2026-03-12",
    "品牌": "菜百",
    "产品": "黄金价格",
    "价格": "1548.00",
    "价格_数值": 1548.0,
    "单位": "元/克",
    "纯度": "--",
    "手工费": "另计",
    "涨跌": "--",
    "黄金类型": "实物黄金",
    "黄金类型代码": "physical",
    "数据来源": "新浪财经",
    "解析时间": "2026-03-20T04:10:45.580853"
  },
  {
    "日期": "2026-03-12",
    "品牌": "周生生",
    "产品": "黄金价格",
    "价格": "1579.00",
    "价格_数值": 1579.0,
    "单位": "元/克",
    "纯度": "--",
    "手工费": "另计",
    "涨跌": "跌",
    "黄金类型": "实物黄金",
    "黄金类型代码": "physical",
    "数据来源": "新浪财经",
    "解析时间": "2026-03-20T04:10:45.580856"
  },
  {
    "日期": "2026-03-12",
    "品牌": "六福",
    "产品": "黄金价格",
    "价格": "1584.00",
    "价格_数值": 1584.0,
    "单位": "元/克",
    "纯度": "--",
    "手工费": "另计",
    "涨跌": "跌",
    "黄金类型": "实物黄金",
    "黄金类型代码": "physical",
    "数据来源": "新浪财经",
    "解析时间": "2026-03-20T04:10:45.580859"
  },
  {
    "日期": "2026-03-12",
    "品牌": "周大福",
    "产品": "黄金价格",
    "价格": "1586.00",
    "价格_数值": 1586.0,
    "单位": "元/克",
    "纯度": "--",
    "手工费": "另计",
    "涨跌": "跌",
    "黄金类型": "实物黄金",
    "黄金类型代码": "physical",
    "数据来源": "新浪财经",
    "解析时间": "2026-03-20T04:10:45.580861"
  },
  {
    "日期": "2026-03-12",
    "品牌": "老庙",
    "产品": "黄金价格",
    "价格": "1580.00",
    "价格_数值": 1580.0,
    "单位": "元/克",
    "纯度": "--",
    "手工费": "另计",
    "涨跌": "跌",
    "黄金类型": "实物黄金",
    "黄金类型代码": "physical",
    "数据来源": "新浪财经",
    "解析时间": "2026-03-20T04:10:45.580864"
  },
  {
    "日期": "2026-03-11",
    "品牌": "周生生",
    "产品": "黄金价格",
    "价格": "1600.00",
    "价格_数值": 1600.0,
    "单位": "元/克",
    "纯度": "--",
    "手工费": "另计",
    "涨跌": "涨",
    "黄金类型": "实物黄金",
    "黄金类型代码": "physical",
    "数据来源": "新浪财经",
    "解析时间": "2026-03-20T04:10:45.580867"
  },
  {
    "日期": "2026-03-11",
    "品牌": "金至尊",
    "产品": "黄金价格",
    "价格": "1597.00",
    "价格_数值": 1597.0,
    "单位": "元/克",
    "纯度": "--",
    "手工费": "另计",
    "涨跌": "涨",
    "黄金类型": "实物黄金",
    "黄金类型代码": "physical",
    "数据来源": "新浪财经",
    "解析时间": "2026-03-20T04:10:45.580870"
  }
]